[
  {
    "id": 1,
    "key": "ವ",
    "isAvailable": true,
    "letterForms": [
      {
        "id": 1,
        "form": "va_form1",
        "path": "va/va_form1/1000_AksharaMeru_Jakkur_3_4_va.jpg",
        "year": 1000
      },
      {
        "id": 2,
        "form": "va_form1",
        "path": "va/va_form1/1000_Cp113_Kudluru_9_3_va.JPG",
        "year": 1000
      },
      {
        "id": 3,
        "form": "va_form1",
        "path": "va/va_form1/1000_IthDar_Kamarasanahalli_1_5_va.JPG",
        "year": 1000
      },
      {
        "id": 4,
        "form": "va_form1",
        "path": "va/va_form1/1306_DB52_Isturu_10_20_va.JPG",
        "year": 1306
      },
      {
        "id": 5,
        "form": "va_form1",
        "path": "va/va_form1/1306_DB52_Isturu_1_14_va.JPG",
        "year": 1306
      },
      {
        "id": 6,
        "form": "va_form1",
        "path": "va/va_form1/1306_DB52_Isturu_1_7_va.JPG",
        "year": 1306
      },
      {
        "id": 7,
        "form": "va_form1",
        "path": "va/va_form1/1306_DB52_Isturu_3_5_va.JPG",
        "year": 1306
      },
      {
        "id": 8,
        "form": "va_form1",
        "path": "va/va_form1/1306_DB52_Isturu_8_13_va.JPG",
        "year": 1306
      },
      {
        "id": 9,
        "form": "va_form1",
        "path": "va/va_form1/1306_DB52_Isturu_8_21_va.JPG",
        "year": 1306
      },
      {
        "id": 10,
        "form": "va_form1",
        "path": "va/va_form1/1306_DB52_Isturu_9_14_va.JPG",
        "year": 1306
      },
      {
        "id": 11,
        "form": "va_form1",
        "path": "va/va_form1/1306_DB52_Isturu_9_28_va.JPG",
        "year": 1306
      },
      {
        "id": 12,
        "form": "va_form1",
        "path": "va/va_form1/1336_Bn120_Katanayakanapura_10_7_va.jpg",
        "year": 1336
      },
      {
        "id": 13,
        "form": "va_form1",
        "path": "va/va_form1/1336_Bn120_Katanayakanapura_11_4_va.jpg",
        "year": 1336
      },
      {
        "id": 14,
        "form": "va_form1",
        "path": "va/va_form1/1336_Bn120_Katanayakanapura_11_6_va.jpg",
        "year": 1336
      },
      {
        "id": 15,
        "form": "va_form1",
        "path": "va/va_form1/1340_Bn111_Ramasamudra_12_3_va.JPG",
        "year": 1340
      },
      {
        "id": 16,
        "form": "va_form1",
        "path": "va/va_form1/1340_Bn111_Ramasamudra_15_18_va.JPG",
        "year": 1340
      },
      {
        "id": 17,
        "form": "va_form1",
        "path": "va/va_form1/1340_Bn111_Ramasamudra_15_3_va.JPG",
        "year": 1340
      },
      {
        "id": 18,
        "form": "va_form1",
        "path": "va/va_form1/1340_Bn111_Ramasamudra_15_8_va.JPG",
        "year": 1340
      },
      {
        "id": 19,
        "form": "va_form1",
        "path": "va/va_form1/1340_Bn111_Ramasamudra_16_15_va.JPG",
        "year": 1340
      },
      {
        "id": 20,
        "form": "va_form1",
        "path": "va/va_form1/1340_Bn111_Ramasamudra_18_2_va.JPG",
        "year": 1340
      },
      {
        "id": 21,
        "form": "va_form1",
        "path": "va/va_form1/1340_Bn111_Ramasamudra_18_8_va.JPG",
        "year": 1340
      },
      {
        "id": 22,
        "form": "va_form1",
        "path": "va/va_form1/1340_Bn111_Ramasamudra_1_17_va.JPG",
        "year": 1340
      },
      {
        "id": 23,
        "form": "va_form1",
        "path": "va/va_form1/1340_Bn111_Ramasamudra_20_5_va.JPG",
        "year": 1340
      },
      {
        "id": 24,
        "form": "va_form1",
        "path": "va/va_form1/1340_Bn111_Ramasamudra_22_11_va.JPG",
        "year": 1340
      },
      {
        "id": 25,
        "form": "va_form1",
        "path": "va/va_form1/1340_Bn111_Ramasamudra_22_3_va.JPG",
        "year": 1340
      },
      {
        "id": 26,
        "form": "va_form1",
        "path": "va/va_form1/1340_Bn111_Ramasamudra_24_10_va.JPG",
        "year": 1340
      },
      {
        "id": 27,
        "form": "va_form1",
        "path": "va/va_form1/1340_Bn111_Ramasamudra_24_1_va.JPG",
        "year": 1340
      },
      {
        "id": 28,
        "form": "va_form1",
        "path": "va/va_form1/1340_Bn111_Ramasamudra_35_3_va.JPG",
        "year": 1340
      },
      {
        "id": 29,
        "form": "va_form1",
        "path": "va/va_form1/1340_Bn111_Ramasamudra_36_15_va.JPG",
        "year": 1340
      },
      {
        "id": 30,
        "form": "va_form1",
        "path": "va/va_form1/1340_Bn111_Ramasamudra_37_15_va.JPG",
        "year": 1340
      },
      {
        "id": 31,
        "form": "va_form1",
        "path": "va/va_form1/1340_Bn111_Ramasamudra_37_8_va.JPG",
        "year": 1340
      },
      {
        "id": 32,
        "form": "va_form1",
        "path": "va/va_form1/1340_Bn111_Ramasamudra_39_15_va.JPG",
        "year": 1340
      },
      {
        "id": 33,
        "form": "va_form1",
        "path": "va/va_form1/1340_Bn111_Ramasamudra_39_1_va.JPG",
        "year": 1340
      },
      {
        "id": 34,
        "form": "va_form1",
        "path": "va/va_form1/1340_Bn111_Ramasamudra_43_12_va.JPG",
        "year": 1340
      },
      {
        "id": 35,
        "form": "va_form1",
        "path": "va/va_form1/1340_Bn111_Ramasamudra_44_3_va.JPG",
        "year": 1340
      },
      {
        "id": 36,
        "form": "va_form1",
        "path": "va/va_form1/1340_Bn111_Ramasamudra_46_17_va.JPG",
        "year": 1340
      },
      {
        "id": 37,
        "form": "va_form1",
        "path": "va/va_form1/1340_Bn111_Ramasamudra_46_4_va.JPG",
        "year": 1340
      },
      {
        "id": 38,
        "form": "va_form1",
        "path": "va/va_form1/1340_Bn111_Ramasamudra_46_8_va.JPG",
        "year": 1340
      },
      {
        "id": 39,
        "form": "va_form1",
        "path": "va/va_form1/1340_Bn111_Ramasamudra_47_8_va.JPG",
        "year": 1340
      },
      {
        "id": 40,
        "form": "va_form1",
        "path": "va/va_form1/1340_Bn111_Ramasamudra_49_11_va.JPG",
        "year": 1340
      },
      {
        "id": 41,
        "form": "va_form1",
        "path": "va/va_form1/1340_Bn111_Ramasamudra_4_15_va.JPG",
        "year": 1340
      },
      {
        "id": 42,
        "form": "va_form1",
        "path": "va/va_form1/1340_Bn111_Ramasamudra_4_4_va.JPG",
        "year": 1340
      },
      {
        "id": 43,
        "form": "va_form1",
        "path": "va/va_form1/1340_Bn111_Ramasamudra_4_8_va.JPG",
        "year": 1340
      },
      {
        "id": 44,
        "form": "va_form1",
        "path": "va/va_form1/1340_Bn111_Ramasamudra_50_11_va.JPG",
        "year": 1340
      },
      {
        "id": 45,
        "form": "va_form1",
        "path": "va/va_form1/1340_Bn111_Ramasamudra_50_14_va.JPG",
        "year": 1340
      },
      {
        "id": 46,
        "form": "va_form1",
        "path": "va/va_form1/1340_Bn111_Ramasamudra_50_6_va.JPG",
        "year": 1340
      },
      {
        "id": 47,
        "form": "va_form1",
        "path": "va/va_form1/1340_Bn111_Ramasamudra_50_9_va.JPG",
        "year": 1340
      },
      {
        "id": 48,
        "form": "va_form1",
        "path": "va/va_form1/1342_BN21_Jakkur_12_9_va.jpg",
        "year": 1342
      },
      {
        "id": 49,
        "form": "va_form1",
        "path": "va/va_form1/1342_BN21_Jakkur_13_6_va.jpg",
        "year": 1342
      },
      {
        "id": 50,
        "form": "va_form1",
        "path": "va/va_form1/1342_BN21_Jakkur_21_4_va.jpg",
        "year": 1342
      },
      {
        "id": 51,
        "form": "va_form1",
        "path": "va/va_form1/1342_BN21_Jakkur_3_10_va.jpg",
        "year": 1342
      },
      {
        "id": 52,
        "form": "va_form1",
        "path": "va/va_form1/1342_BN21_Jakkur_5_2_va.jpg",
        "year": 1342
      },
      {
        "id": 53,
        "form": "va_form1",
        "path": "va/va_form1/1353_IthDar_Bidarahalli_13_6_va.JPG",
        "year": 1353
      },
      {
        "id": 54,
        "form": "va_form1",
        "path": "va/va_form1/1370_IthDar_DoddaGubbi_10_9_va.jpg",
        "year": 1370
      },
      {
        "id": 55,
        "form": "va_form1",
        "path": "va/va_form1/1370_IthDar_DoddaGubbi_2_9_va.jpg",
        "year": 1370
      },
      {
        "id": 56,
        "form": "va_form1",
        "path": "va/va_form1/1516_IthDar_Rayasandra_2_11_va.JPG",
        "year": 1516
      },
      {
        "id": 57,
        "form": "va_form1",
        "path": "va/va_form1/1516_IthDar_Rayasandra_4_3_va.JPG",
        "year": 1516
      },
      {
        "id": 58,
        "form": "va_form2",
        "path": "va/va_form2/1306_DB52_Isturu_3_9_va.JPG",
        "year": 1306
      },
      {
        "id": 59,
        "form": "va_form2",
        "path": "va/va_form2/1306_DB52_Isturu_6_14_va.JPG",
        "year": 1306
      },
      {
        "id": 60,
        "form": "va_form2",
        "path": "va/va_form2/1329_IthDar_Kadatanamale_10_2_va.JPG",
        "year": 1329
      },
      {
        "id": 61,
        "form": "va_form2",
        "path": "va/va_form2/1329_IthDar_Kadatanamale_1_6_va.JPG",
        "year": 1329
      },
      {
        "id": 62,
        "form": "va_form2",
        "path": "va/va_form2/1329_IthDar_Kadatanamale_2_6_va.JPG",
        "year": 1329
      },
      {
        "id": 63,
        "form": "va_form2",
        "path": "va/va_form2/1329_IthDar_Kadatanamale_3_13_va.JPG",
        "year": 1329
      },
      {
        "id": 64,
        "form": "va_form2",
        "path": "va/va_form2/1329_IthDar_Kadatanamale_5_6_va.JPG",
        "year": 1329
      },
      {
        "id": 65,
        "form": "va_form2",
        "path": "va/va_form2/1336_Bn110_Byadarahalli_11_12_va.JPG",
        "year": 1336
      },
      {
        "id": 66,
        "form": "va_form2",
        "path": "va/va_form2/1336_Bn110_Byadarahalli_11_1_va.JPG",
        "year": 1336
      },
      {
        "id": 67,
        "form": "va_form2",
        "path": "va/va_form2/1336_Bn110_Byadarahalli_11_5_va.JPG",
        "year": 1336
      },
      {
        "id": 68,
        "form": "va_form2",
        "path": "va/va_form2/1336_Bn110_Byadarahalli_12_10_va.JPG",
        "year": 1336
      },
      {
        "id": 69,
        "form": "va_form2",
        "path": "va/va_form2/1336_Bn110_Byadarahalli_12_16_va.JPG",
        "year": 1336
      },
      {
        "id": 70,
        "form": "va_form2",
        "path": "va/va_form2/1336_Bn110_Byadarahalli_13_14_va.JPG",
        "year": 1336
      },
      {
        "id": 71,
        "form": "va_form2",
        "path": "va/va_form2/1336_Bn110_Byadarahalli_16_11_va.JPG",
        "year": 1336
      },
      {
        "id": 72,
        "form": "va_form2",
        "path": "va/va_form2/1336_Bn110_Byadarahalli_17_2_va.JPG",
        "year": 1336
      },
      {
        "id": 73,
        "form": "va_form2",
        "path": "va/va_form2/1336_Bn110_Byadarahalli_18_8_va.JPG",
        "year": 1336
      },
      {
        "id": 74,
        "form": "va_form2",
        "path": "va/va_form2/1336_Bn110_Byadarahalli_19_17_va.JPG",
        "year": 1336
      },
      {
        "id": 75,
        "form": "va_form2",
        "path": "va/va_form2/1336_Bn110_Byadarahalli_19_6_va.JPG",
        "year": 1336
      },
      {
        "id": 76,
        "form": "va_form2",
        "path": "va/va_form2/1336_Bn110_Byadarahalli_1_7_va.JPG",
        "year": 1336
      },
      {
        "id": 77,
        "form": "va_form2",
        "path": "va/va_form2/1336_Bn110_Byadarahalli_21_16_va.JPG",
        "year": 1336
      },
      {
        "id": 78,
        "form": "va_form2",
        "path": "va/va_form2/1336_Bn110_Byadarahalli_22_10_va.JPG",
        "year": 1336
      },
      {
        "id": 79,
        "form": "va_form2",
        "path": "va/va_form2/1336_Bn110_Byadarahalli_22_12_va.JPG",
        "year": 1336
      },
      {
        "id": 80,
        "form": "va_form2",
        "path": "va/va_form2/1336_Bn110_Byadarahalli_2_4_va.JPG",
        "year": 1336
      },
      {
        "id": 81,
        "form": "va_form2",
        "path": "va/va_form2/1336_Bn110_Byadarahalli_34_1_va.JPG",
        "year": 1336
      },
      {
        "id": 82,
        "form": "va_form2",
        "path": "va/va_form2/1336_Bn110_Byadarahalli_37_10_va.JPG",
        "year": 1336
      },
      {
        "id": 83,
        "form": "va_form2",
        "path": "va/va_form2/1336_Bn110_Byadarahalli_45_4_va.JPG",
        "year": 1336
      },
      {
        "id": 84,
        "form": "va_form2",
        "path": "va/va_form2/1336_Bn110_Byadarahalli_48_4_va.JPG",
        "year": 1336
      },
      {
        "id": 85,
        "form": "va_form2",
        "path": "va/va_form2/1336_Bn110_Byadarahalli_4_5_va.JPG",
        "year": 1336
      },
      {
        "id": 86,
        "form": "va_form2",
        "path": "va/va_form2/1336_Bn110_Byadarahalli_9_15_va.JPG",
        "year": 1336
      },
      {
        "id": 87,
        "form": "va_form2",
        "path": "va/va_form2/1336_Bn120_Katanayakanapura_10_15_va.jpg",
        "year": 1336
      },
      {
        "id": 88,
        "form": "va_form2",
        "path": "va/va_form2/1336_Bn120_Katanayakanapura_4_7_va.jpg",
        "year": 1336
      },
      {
        "id": 89,
        "form": "va_form2",
        "path": "va/va_form2/1336_Bn120_Katanayakanapura_6_12_va.jpg",
        "year": 1336
      },
      {
        "id": 90,
        "form": "va_form2",
        "path": "va/va_form2/1336_DV46_Sadenahalli_1_6_va.JPG",
        "year": 1336
      },
      {
        "id": 91,
        "form": "va_form2",
        "path": "va/va_form2/1336_DV46_Sadenahalli_3_5_va.JPG",
        "year": 1336
      },
      {
        "id": 92,
        "form": "va_form2",
        "path": "va/va_form2/1336_DV46_Sadenahalli_5_6_va.JPG",
        "year": 1336
      },
      {
        "id": 93,
        "form": "va_form2",
        "path": "va/va_form2/1336_DV46_Sadenahalli_6_12_va.JPG",
        "year": 1336
      },
      {
        "id": 94,
        "form": "va_form2",
        "path": "va/va_form2/1340_Bn111_Ramasamudra_21_6_va.JPG",
        "year": 1340
      },
      {
        "id": 95,
        "form": "va_form2",
        "path": "va/va_form2/1340_Bn111_Ramasamudra_2_14_va.JPG",
        "year": 1340
      },
      {
        "id": 96,
        "form": "va_form2",
        "path": "va/va_form2/1340_Bn111_Ramasamudra_3_3_va.JPG",
        "year": 1340
      },
      {
        "id": 97,
        "form": "va_form2",
        "path": "va/va_form2/1340_Bn111_Ramasamudra_9_8_va.JPG",
        "year": 1340
      },
      {
        "id": 98,
        "form": "va_form2",
        "path": "va/va_form2/1342_BN21_Jakkur_20_5_va.jpg",
        "year": 1342
      },
      {
        "id": 99,
        "form": "va_form2",
        "path": "va/va_form2/1342_BN21_Jakkur_9_6_va.jpg",
        "year": 1342
      },
      {
        "id": 100,
        "form": "va_form2",
        "path": "va/va_form2/1342_BN24_Ganigarahalli_1_5_va.JPG",
        "year": 1342
      },
      {
        "id": 101,
        "form": "va_form2",
        "path": "va/va_form2/1342_BN24_Ganigarahalli_2_4_va.JPG",
        "year": 1342
      },
      {
        "id": 102,
        "form": "va_form2",
        "path": "va/va_form2/1342_BN24_Ganigarahalli_9_4_va.JPG",
        "year": 1342
      },
      {
        "id": 103,
        "form": "va_form2",
        "path": "va/va_form2/1345_Dv3_Jalige_1_6_va.jpg",
        "year": 1345
      },
      {
        "id": 104,
        "form": "va_form2",
        "path": "va/va_form2/1345_Dv3_Jalige_2_7_va.jpg",
        "year": 1345
      },
      {
        "id": 105,
        "form": "va_form2",
        "path": "va/va_form2/1345_Dv3_Jalige_5_6_va.jpg",
        "year": 1345
      },
      {
        "id": 106,
        "form": "va_form2",
        "path": "va/va_form2/1353_IthDar_Bidarahalli_5_2_va.JPG",
        "year": 1353
      },
      {
        "id": 107,
        "form": "va_form2",
        "path": "va/va_form2/1353_IthDar_Bidarahalli_8_3_va.JPG",
        "year": 1353
      },
      {
        "id": 108,
        "form": "va_form2",
        "path": "va/va_form2/1363_BN81_AgaraMuseum_10_17_va.JPG",
        "year": 1363
      },
      {
        "id": 109,
        "form": "va_form2",
        "path": "va/va_form2/1363_BN81_AgaraMuseum_12_9_va.JPG",
        "year": 1363
      },
      {
        "id": 110,
        "form": "va_form2",
        "path": "va/va_form2/1363_BN81_AgaraMuseum_16_8_va.JPG",
        "year": 1363
      },
      {
        "id": 111,
        "form": "va_form2",
        "path": "va/va_form2/1363_BN81_AgaraMuseum_4_10_va.JPG",
        "year": 1363
      },
      {
        "id": 112,
        "form": "va_form2",
        "path": "va/va_form2/1369_CP150_Malurpatna_10_6_va.JPG",
        "year": 1369
      },
      {
        "id": 113,
        "form": "va_form2",
        "path": "va/va_form2/1369_CP150_Malurpatna_12_9_va.JPG",
        "year": 1369
      },
      {
        "id": 114,
        "form": "va_form2",
        "path": "va/va_form2/1369_CP150_Malurpatna_13_1_va.JPG",
        "year": 1369
      },
      {
        "id": 115,
        "form": "va_form2",
        "path": "va/va_form2/1369_CP150_Malurpatna_13_8_va.JPG",
        "year": 1369
      },
      {
        "id": 116,
        "form": "va_form2",
        "path": "va/va_form2/1369_CP150_Malurpatna_14_6_va.JPG",
        "year": 1369
      },
      {
        "id": 117,
        "form": "va_form2",
        "path": "va/va_form2/1369_CP150_Malurpatna_15_14_va.JPG",
        "year": 1369
      },
      {
        "id": 118,
        "form": "va_form2",
        "path": "va/va_form2/1369_CP150_Malurpatna_16_6_va.JPG",
        "year": 1369
      },
      {
        "id": 119,
        "form": "va_form2",
        "path": "va/va_form2/1369_CP150_Malurpatna_2_7_va.JPG",
        "year": 1369
      },
      {
        "id": 120,
        "form": "va_form2",
        "path": "va/va_form2/1369_CP150_Malurpatna_5_13_va.JPG",
        "year": 1369
      },
      {
        "id": 121,
        "form": "va_form2",
        "path": "va/va_form2/1369_CP150_Malurpatna_6_19_va.JPG",
        "year": 1369
      },
      {
        "id": 122,
        "form": "va_form2",
        "path": "va/va_form2/1369_CP150_Malurpatna_7_6_va.JPG",
        "year": 1369
      },
      {
        "id": 123,
        "form": "va_form2",
        "path": "va/va_form2/1369_CP150_Malurpatna_8_3_va.JPG",
        "year": 1369
      },
      {
        "id": 124,
        "form": "va_form2",
        "path": "va/va_form2/1369_CP150_Malurpatna_9_16_va.JPG",
        "year": 1369
      },
      {
        "id": 125,
        "form": "va_form2",
        "path": "va/va_form2/1370_IthDar_DoddaGubbi_4_7_va.jpg",
        "year": 1370
      },
      {
        "id": 126,
        "form": "va_form2",
        "path": "va/va_form2/1370_IthDar_DoddaGubbi_6_8_va.jpg",
        "year": 1370
      },
      {
        "id": 127,
        "form": "va_form2",
        "path": "va/va_form2/1382_DV57_Chikkajala_1_6_va.JPG",
        "year": 1382
      },
      {
        "id": 128,
        "form": "va_form2",
        "path": "va/va_form2/1382_DV57_Chikkajala_2_10_va.JPG",
        "year": 1382
      },
      {
        "id": 129,
        "form": "va_form2",
        "path": "va/va_form2/1382_DV57_Chikkajala_2_6_va.JPG",
        "year": 1382
      },
      {
        "id": 130,
        "form": "va_form2",
        "path": "va/va_form2/1382_DV57_Chikkajala_4_1_va.JPG",
        "year": 1382
      },
      {
        "id": 131,
        "form": "va_form2",
        "path": "va/va_form2/1382_DV57_Chikkajala_4_7_va.JPG",
        "year": 1382
      },
      {
        "id": 132,
        "form": "va_form2",
        "path": "va/va_form2/1388_MG20_HuleLinganaAre_1_14_va.JPG",
        "year": 1388
      },
      {
        "id": 133,
        "form": "va_form2",
        "path": "va/va_form2/1388_MG20_HuleLinganaAre_1_25_va.JPG",
        "year": 1388
      },
      {
        "id": 134,
        "form": "va_form2",
        "path": "va/va_form2/1388_MG20_HuleLinganaAre_1_27_va.JPG",
        "year": 1388
      },
      {
        "id": 135,
        "form": "va_form2",
        "path": "va/va_form2/1400_Bn90_Begurdoorpost_2_4_va.jpg",
        "year": 1400
      },
      {
        "id": 136,
        "form": "va_form2",
        "path": "va/va_form2/1400_Bommenhallli_Unpub_1_6_va.JPG",
        "year": 1400
      },
      {
        "id": 137,
        "form": "va_form2",
        "path": "va/va_form2/1400_Bommenhallli_Unpub_3_1_va.JPG",
        "year": 1400
      },
      {
        "id": 138,
        "form": "va_form2",
        "path": "va/va_form2/1400_Bommenhallli_Unpub_6_7_va.JPG",
        "year": 1400
      },
      {
        "id": 139,
        "form": "va_form2",
        "path": "va/va_form2/1400_Hennagara_Unpub_4_7_va.JPG",
        "year": 1400
      },
      {
        "id": 140,
        "form": "va_form3",
        "path": "va/va_form3/1342_BN24_Ganigarahalli_11_15_va.JPG",
        "year": 1342
      },
      {
        "id": 141,
        "form": "va_form3",
        "path": "va/va_form3/1342_BN24_Ganigarahalli_11_1_va.JPG",
        "year": 1342
      },
      {
        "id": 142,
        "form": "va_form3",
        "path": "va/va_form3/1342_BN24_Ganigarahalli_12_13_va.JPG",
        "year": 1342
      },
      {
        "id": 143,
        "form": "va_form3",
        "path": "va/va_form3/1342_BN24_Ganigarahalli_13_15_va.JPG",
        "year": 1342
      },
      {
        "id": 144,
        "form": "va_form3",
        "path": "va/va_form3/1342_BN24_Ganigarahalli_14_18_va.JPG",
        "year": 1342
      },
      {
        "id": 145,
        "form": "va_form3",
        "path": "va/va_form3/1342_BN24_Ganigarahalli_14_7_va.JPG",
        "year": 1342
      },
      {
        "id": 146,
        "form": "va_form3",
        "path": "va/va_form3/1342_BN24_Ganigarahalli_15_5_va.JPG",
        "year": 1342
      },
      {
        "id": 147,
        "form": "va_form3",
        "path": "va/va_form3/1342_BN24_Ganigarahalli_16_7_va.JPG",
        "year": 1342
      },
      {
        "id": 148,
        "form": "va_form3",
        "path": "va/va_form3/1342_BN24_Ganigarahalli_2_11_va.JPG",
        "year": 1342
      },
      {
        "id": 149,
        "form": "va_form3",
        "path": "va/va_form3/1342_BN24_Ganigarahalli_4_8_va.JPG",
        "year": 1342
      },
      {
        "id": 150,
        "form": "va_form3",
        "path": "va/va_form3/1342_BN24_Ganigarahalli_5_11_va.JPG",
        "year": 1342
      },
      {
        "id": 151,
        "form": "va_form4",
        "path": "va/va_form4/1382_DV57_Chikkajala_3_14_va.JPG",
        "year": 1382
      },
      {
        "id": 152,
        "form": "va_form5",
        "path": "va/va_form5/1306_DB52_Isturu_3_16_va.JPG",
        "year": 1306
      }
    ],
    "IASTform": ""
  },
  {
    "id": 2,
    "key": "ವಾ",
    "isAvailable": true,
    "letterForms": [
      {
        "id": 1,
        "form": "vā_form1",
        "path": "vā/vā_form1/1340_Bn111_Ramasamudra_37_18_vā.JPG",
        "year": 1340
      },
      {
        "id": 2,
        "form": "vā_form1",
        "path": "vā/vā_form1/1516_IthDar_Rayasandra_2_6_vā.JPG",
        "year": 1516
      },
      {
        "id": 3,
        "form": "vā_form2",
        "path": "vā/vā_form2/1306_DB52_Isturu_5_21_vā.JPG",
        "year": 1306
      },
      {
        "id": 4,
        "form": "vā_form2",
        "path": "vā/vā_form2/1336_Bn110_Byadarahalli_35_8_vā.JPG",
        "year": 1336
      },
      {
        "id": 5,
        "form": "vā_form2",
        "path": "vā/vā_form2/1336_Bn110_Byadarahalli_8_8_vā.JPG",
        "year": 1336
      },
      {
        "id": 6,
        "form": "vā_form2",
        "path": "vā/vā_form2/1336_Bn120_Katanayakanapura_1_15_vā.JPG",
        "year": 1336
      },
      {
        "id": 7,
        "form": "vā_form2",
        "path": "vā/vā_form2/1336_Bn120_Katanayakanapura_7_11_vā.jpg",
        "year": 1336
      },
      {
        "id": 8,
        "form": "vā_form2",
        "path": "vā/vā_form2/1336_DV46_Sadenahalli_4_5_vā.JPG",
        "year": 1336
      },
      {
        "id": 9,
        "form": "vā_form2",
        "path": "vā/vā_form2/1340_Bn111_Ramasamudra_11_8_vā.JPG",
        "year": 1340
      },
      {
        "id": 10,
        "form": "vā_form2",
        "path": "vā/vā_form2/1340_Bn111_Ramasamudra_40_16_vā.JPG",
        "year": 1340
      },
      {
        "id": 11,
        "form": "vā_form2",
        "path": "vā/vā_form2/1340_Bn111_Ramasamudra_9_19_vā.JPG",
        "year": 1340
      },
      {
        "id": 12,
        "form": "vā_form2",
        "path": "vā/vā_form2/1342_BN24_Ganigarahalli_18_11_vā.JPG",
        "year": 1342
      },
      {
        "id": 13,
        "form": "vā_form2",
        "path": "vā/vā_form2/1345_Dv3_Jalige_3_8_vā.jpg",
        "year": 1345
      },
      {
        "id": 14,
        "form": "vā_form2",
        "path": "vā/vā_form2/1370_IthDar_DoddaGubbi_3_8_vā.jpg",
        "year": 1370
      },
      {
        "id": 15,
        "form": "vā_form2",
        "path": "vā/vā_form2/1388_MG20_HuleLinganaAre_3_12_vā.JPG",
        "year": 1388
      },
      {
        "id": 16,
        "form": "vā_form2",
        "path": "vā/vā_form2/1400_Bn90_Begurdoorpost_10_2_vā.jpg",
        "year": 1400
      }
    ],
    "IASTform": ""
  },
  {
    "id": 3,
    "key": "ವಿ",
    "isAvailable": true,
    "letterForms": [
      {
        "id": 1,
        "form": "vi_form1",
        "path": "vi/vi_form1/1000_AksharaMeru_Jakkur_4_6_vi.jpg",
        "year": 1000
      },
      {
        "id": 2,
        "form": "vi_form1",
        "path": "vi/vi_form1/1000_Bp65_Karubele_2_5_vi.JPG",
        "year": 1000
      },
      {
        "id": 3,
        "form": "vi_form1",
        "path": "vi/vi_form1/1306_DB52_Isturu_9_15_vi.JPG",
        "year": 1306
      },
      {
        "id": 4,
        "form": "vi_form1",
        "path": "vi/vi_form1/1329_IthDar_Kadatanamale_7_5_vi.JPG",
        "year": 1329
      },
      {
        "id": 5,
        "form": "vi_form1",
        "path": "vi/vi_form1/1336_Bn110_Byadarahalli_20_14_vi.JPG",
        "year": 1336
      },
      {
        "id": 6,
        "form": "vi_form1",
        "path": "vi/vi_form1/1336_Bn110_Byadarahalli_21_11_vi.JPG",
        "year": 1336
      },
      {
        "id": 7,
        "form": "vi_form1",
        "path": "vi/vi_form1/1336_Bn110_Byadarahalli_21_5_vi.JPG",
        "year": 1336
      },
      {
        "id": 8,
        "form": "vi_form1",
        "path": "vi/vi_form1/1336_Bn110_Byadarahalli_25_13_vi.JPG",
        "year": 1336
      },
      {
        "id": 9,
        "form": "vi_form1",
        "path": "vi/vi_form1/1336_Bn110_Byadarahalli_2_3_vi.JPG",
        "year": 1336
      },
      {
        "id": 10,
        "form": "vi_form1",
        "path": "vi/vi_form1/1336_Bn110_Byadarahalli_41_12_vi.JPG",
        "year": 1336
      },
      {
        "id": 11,
        "form": "vi_form1",
        "path": "vi/vi_form1/1336_DV46_Sadenahalli_8_8_vi.JPG",
        "year": 1336
      },
      {
        "id": 12,
        "form": "vi_form1",
        "path": "vi/vi_form1/1340_Bn111_Ramasamudra_15_6_vi.JPG",
        "year": 1340
      },
      {
        "id": 13,
        "form": "vi_form1",
        "path": "vi/vi_form1/1340_Bn111_Ramasamudra_16_5_vi.JPG",
        "year": 1340
      },
      {
        "id": 14,
        "form": "vi_form1",
        "path": "vi/vi_form1/1340_Bn111_Ramasamudra_17_19_vi.JPG",
        "year": 1340
      },
      {
        "id": 15,
        "form": "vi_form1",
        "path": "vi/vi_form1/1340_Bn111_Ramasamudra_1_13_vi.JPG",
        "year": 1340
      },
      {
        "id": 16,
        "form": "vi_form1",
        "path": "vi/vi_form1/1340_Bn111_Ramasamudra_33_12_vi.JPG",
        "year": 1340
      },
      {
        "id": 17,
        "form": "vi_form1",
        "path": "vi/vi_form1/1340_Bn111_Ramasamudra_3_2_vi.JPG",
        "year": 1340
      },
      {
        "id": 18,
        "form": "vi_form1",
        "path": "vi/vi_form1/1340_Bn111_Ramasamudra_40_4_vi.JPG",
        "year": 1340
      },
      {
        "id": 19,
        "form": "vi_form1",
        "path": "vi/vi_form1/1340_Bn111_Ramasamudra_42_9_vi.JPG",
        "year": 1340
      },
      {
        "id": 20,
        "form": "vi_form1",
        "path": "vi/vi_form1/1340_Bn111_Ramasamudra_8_15_vi.JPG",
        "year": 1340
      },
      {
        "id": 21,
        "form": "vi_form1",
        "path": "vi/vi_form1/1353_IthDar_Bidarahalli_2_3_vi.JPG",
        "year": 1353
      },
      {
        "id": 22,
        "form": "vi_form1",
        "path": "vi/vi_form1/1353_IthDar_Bidarahalli_4_4_vi.JPG",
        "year": 1353
      },
      {
        "id": 23,
        "form": "vi_form1",
        "path": "vi/vi_form1/1363_BN81_AgaraMuseum_4_2_vi.JPG",
        "year": 1363
      },
      {
        "id": 24,
        "form": "vi_form1",
        "path": "vi/vi_form1/1369_CP150_Malurpatna_12_10_vi.JPG",
        "year": 1369
      },
      {
        "id": 25,
        "form": "vi_form1",
        "path": "vi/vi_form1/1369_CP150_Malurpatna_15_8_vi.JPG",
        "year": 1369
      },
      {
        "id": 26,
        "form": "vi_form1",
        "path": "vi/vi_form1/1369_CP150_Malurpatna_16_1_vi.JPG",
        "year": 1369
      },
      {
        "id": 27,
        "form": "vi_form1",
        "path": "vi/vi_form1/1369_CP150_Malurpatna_1_17_vi.JPG",
        "year": 1369
      },
      {
        "id": 28,
        "form": "vi_form1",
        "path": "vi/vi_form1/1369_CP150_Malurpatna_8_7_vi.JPG",
        "year": 1369
      },
      {
        "id": 29,
        "form": "vi_form1",
        "path": "vi/vi_form1/1382_DV57_Chikkajala_1_10_vi.JPG",
        "year": 1382
      },
      {
        "id": 30,
        "form": "vi_form1",
        "path": "vi/vi_form1/1382_DV57_Chikkajala_3_10_vi.JPG",
        "year": 1382
      },
      {
        "id": 31,
        "form": "vi_form1",
        "path": "vi/vi_form1/1388_MG20_HuleLinganaAre_1_23_vi.JPG",
        "year": 1388
      },
      {
        "id": 32,
        "form": "vi_form1",
        "path": "vi/vi_form1/1388_MG20_HuleLinganaAre_1_3_ vi.JPG",
        "year": 1388
      },
      {
        "id": 33,
        "form": "vi_form1",
        "path": "vi/vi_form1/1388_MG20_HuleLinganaAre_3_3_vi.JPG",
        "year": 1388
      },
      {
        "id": 34,
        "form": "vi_form1",
        "path": "vi/vi_form1/1400_Bommenhallli_Unpub_3_5_vi.JPG",
        "year": 1400
      },
      {
        "id": 35,
        "form": "vi_form1",
        "path": "vi/vi_form1/1400_Hennagara_Unpub_3_10_vi.JPG",
        "year": 1400
      }
    ],
    "IASTform": ""
  },
  {
    "id": 4,
    "key": "ವೀ",
    "isAvailable": true,
    "letterForms": [
      {
        "id": 1,
        "form": "vī_form1",
        "path": "vī/vī_form1/1306_DB52_Isturu_5_12_vī.JPG",
        "year": 1306
      },
      {
        "id": 2,
        "form": "vī_form1",
        "path": "vī/vī_form1/1306_DB52_Isturu_8_15_vī.JPG",
        "year": 1306
      },
      {
        "id": 3,
        "form": "vī_form1",
        "path": "vī/vī_form1/1329_IthDar_Kadatanamale_4_11_vī.JPG",
        "year": 1329
      },
      {
        "id": 4,
        "form": "vī_form1",
        "path": "vī/vī_form1/1336_Bn110_Byadarahalli_18_15_vī.JPG",
        "year": 1336
      },
      {
        "id": 5,
        "form": "vī_form1",
        "path": "vī/vī_form1/1336_Bn110_Byadarahalli_19_11_vī.JPG",
        "year": 1336
      },
      {
        "id": 6,
        "form": "vī_form1",
        "path": "vī/vī_form1/1336_Bn110_Byadarahalli_8_4_vī.JPG",
        "year": 1336
      },
      {
        "id": 7,
        "form": "vī_form1",
        "path": "vī/vī_form1/1336_DV46_Sadenahalli_6_6_vī.JPG",
        "year": 1336
      },
      {
        "id": 8,
        "form": "vī_form1",
        "path": "vī/vī_form1/1340_Bn111_Ramasamudra_11_4_vī.JPG",
        "year": 1340
      },
      {
        "id": 9,
        "form": "vī_form1",
        "path": "vī/vī_form1/1340_Bn111_Ramasamudra_15_12_vī.JPG",
        "year": 1340
      },
      {
        "id": 10,
        "form": "vī_form1",
        "path": "vī/vī_form1/1340_Bn111_Ramasamudra_22_14_vī.JPG",
        "year": 1340
      },
      {
        "id": 11,
        "form": "vī_form1",
        "path": "vī/vī_form1/1342_BN21_Jakkur_4_6_vī.jpg",
        "year": 1342
      },
      {
        "id": 12,
        "form": "vī_form1",
        "path": "vī/vī_form1/1342_BN24_Ganigarahalli_5_5_vī.JPG",
        "year": 1342
      },
      {
        "id": 13,
        "form": "vī_form1",
        "path": "vī/vī_form1/1353_IthDar_Bidarahalli_9_3_vī.JPG",
        "year": 1353
      },
      {
        "id": 14,
        "form": "vī_form1",
        "path": "vī/vī_form1/1363_BN81_AgaraMuseum_5_2_vī.JPG",
        "year": 1363
      },
      {
        "id": 15,
        "form": "vī_form1",
        "path": "vī/vī_form1/1369_CP150_Malurpatna_15_10_vī.JPG",
        "year": 1369
      },
      {
        "id": 16,
        "form": "vī_form1",
        "path": "vī/vī_form1/1369_CP150_Malurpatna_15_19_vī.JPG",
        "year": 1369
      },
      {
        "id": 17,
        "form": "vī_form1",
        "path": "vī/vī_form1/1369_CP150_Malurpatna_3_1_vī.JPG",
        "year": 1369
      },
      {
        "id": 18,
        "form": "vī_form1",
        "path": "vī/vī_form1/1369_CP150_Malurpatna_4_1_vī.JPG",
        "year": 1369
      },
      {
        "id": 19,
        "form": "vī_form1",
        "path": "vī/vī_form1/1382_DV57_Chikkajala_5_12_vī.JPG",
        "year": 1382
      },
      {
        "id": 20,
        "form": "vī_form1",
        "path": "vī/vī_form1/1388_MG20_HuleLinganaAre_2_27_vī.JPG",
        "year": 1388
      },
      {
        "id": 21,
        "form": "vī_form1",
        "path": "vī/vī_form1/1400_Bommenhallli_Unpub_7_5_vī.JPG",
        "year": 1400
      },
      {
        "id": 22,
        "form": "vī_form1",
        "path": "vī/vī_form1/1400_Hennagara_Unpub_5_12_vī.JPG",
        "year": 1400
      }
    ],
    "IASTform": ""
  },
  {
    "id": 5,
    "key": "ವು",
    "isAvailable": true,
    "letterForms": [
      {
        "id": 1,
        "form": "vu_form1",
        "path": "vu/vu_form1/1336_Bn110_Byadarahalli_27_9_vu.JPG",
        "year": 1336
      },
      {
        "id": 2,
        "form": "vu_form1",
        "path": "vu/vu_form1/1336_Bn110_Byadarahalli_28_8_vu.JPG",
        "year": 1336
      },
      {
        "id": 3,
        "form": "vu_form1",
        "path": "vu/vu_form1/1336_Bn110_Byadarahalli_29_14_vu.JPG",
        "year": 1336
      },
      {
        "id": 4,
        "form": "vu_form1",
        "path": "vu/vu_form1/1336_Bn110_Byadarahalli_32_7_vu.JPG",
        "year": 1336
      },
      {
        "id": 5,
        "form": "vu_form1",
        "path": "vu/vu_form1/1336_Bn110_Byadarahalli_44_6_vu.JPG",
        "year": 1336
      },
      {
        "id": 6,
        "form": "vu_form1",
        "path": "vu/vu_form1/1340_Bn111_Ramasamudra_39_18_vu.JPG",
        "year": 1340
      },
      {
        "id": 7,
        "form": "vu_form1",
        "path": "vu/vu_form1/1342_BN21_Jakkur_8_7_vu.jpg",
        "year": 1342
      },
      {
        "id": 8,
        "form": "vu_form1",
        "path": "vu/vu_form1/1342_BN24_Ganigarahalli_11_20_vu.JPG",
        "year": 1342
      },
      {
        "id": 9,
        "form": "vu_form1",
        "path": "vu/vu_form1/1342_BN24_Ganigarahalli_11_5_vu.JPG",
        "year": 1342
      },
      {
        "id": 10,
        "form": "vu_form1",
        "path": "vu/vu_form1/1342_BN24_Ganigarahalli_13_5_vu.JPG",
        "year": 1342
      },
      {
        "id": 11,
        "form": "vu_form1",
        "path": "vu/vu_form1/1342_BN24_Ganigarahalli_5_15_vu.JPG",
        "year": 1342
      },
      {
        "id": 12,
        "form": "vu_form1",
        "path": "vu/vu_form1/1342_BN24_Ganigarahalli_7_3_vu.JPG",
        "year": 1342
      },
      {
        "id": 13,
        "form": "vu_form1",
        "path": "vu/vu_form1/1363_BN81_AgaraMuseum_17_2_vu.JPG",
        "year": 1363
      },
      {
        "id": 14,
        "form": "vu_form1",
        "path": "vu/vu_form1/1363_BN81_AgaraMuseum_8_15_vu.JPG",
        "year": 1363
      }
    ],
    "IASTform": ""
  },
  {
    "id": 6,
    "key": "ವೂ",
    "isAvailable": true,
    "letterForms": [
      {
        "id": 1,
        "form": "vū_form1",
        "path": "vū/vū_form1/1336_Bn110_Byadarahalli_35_11_vū.JPG",
        "year": 1336
      },
      {
        "id": 2,
        "form": "vū_form2",
        "path": "vū/vū_form2/1363_BN81_AgaraMuseum_13_2_vū.JPG",
        "year": 1363
      },
      {
        "id": 3,
        "form": "vū_form3",
        "path": "vū/vū_form3/1369_CP150_Malurpatna_6_3_vū.JPG",
        "year": 1369
      }
    ],
    "IASTform": ""
  },
  {
    "id": 7,
    "key": "ವೆ",
    "isAvailable": true,
    "letterForms": [
      {
        "id": 1,
        "form": "ve_form1",
        "path": "ve/ve_form1/1306_DB52_Isturu_9_22_ve.JPG",
        "year": 1306
      },
      {
        "id": 2,
        "form": "ve_form1",
        "path": "ve/ve_form1/1306_DB52_Isturu_9_24_ve.JPG",
        "year": 1306
      },
      {
        "id": 3,
        "form": "ve_form1",
        "path": "ve/ve_form1/1369_CP150_Malurpatna_8_12_ve.JPG",
        "year": 1369
      }
    ],
    "IASTform": ""
  },
  {
    "id": 8,
    "key": "ವೇ",
    "isAvailable": false,
    "letterForms": [],
    "IASTform": ""
  },
  {
    "id": 9,
    "key": "ವೊ",
    "isAvailable": false,
    "letterForms": [],
    "IASTform": ""
  },
  {
    "id": 10,
    "key": "ವೋ",
    "isAvailable": false,
    "letterForms": [],
    "IASTform": ""
  },
  {
    "id": 11,
    "key": "ವೈ",
    "isAvailable": true,
    "letterForms": [
      {
        "id": 1,
        "form": "vai_form1",
        "path": "vai/vai_form1/1340_Bn111_Ramasamudra_11_18_vai.JPG",
        "year": 1340
      },
      {
        "id": 2,
        "form": "vai_form1",
        "path": "vai/vai_form1/1340_Bn111_Ramasamudra_24_11_vai.JPG",
        "year": 1340
      },
      {
        "id": 3,
        "form": "vai_form1",
        "path": "vai/vai_form1/1516_IthDar_Rayasandra_4_7_vai.JPG",
        "year": 1516
      }
    ],
    "IASTform": ""
  },
  {
    "id": 12,
    "key": "ವೌ",
    "isAvailable": false,
    "letterForms": [],
    "IASTform": ""
  },
  {
    "id": 13,
    "key": "ವೃ",
    "isAvailable": false,
    "letterForms": [],
    "IASTform": ""
  },
  {
    "id": 14,
    "key": "ವಃ",
    "isAvailable": false,
    "letterForms": [],
    "IASTform": ""
  },
  {
    "id": 15,
    "key": "ವಂ",
    "isAvailable": true,
    "letterForms": [
      {
        "id": 1,
        "form": "vaṃ_form1",
        "path": "vaṃ/vaṃ_form1/1000_AksharaMeru_Jakkur_4_4_vaṃ.jpg",
        "year": 1000
      },
      {
        "id": 2,
        "form": "vaṃ_form1",
        "path": "vaṃ/vaṃ_form1/1306_DB52_Isturu_6_20_vaṃ.JPG",
        "year": 1306
      },
      {
        "id": 3,
        "form": "vaṃ_form1",
        "path": "vaṃ/vaṃ_form1/1340_Bn111_Ramasamudra_39_7_vaṃ.JPG",
        "year": 1340
      },
      {
        "id": 4,
        "form": "vaṃ_form1",
        "path": "vaṃ/vaṃ_form1/1340_Bn111_Ramasamudra_40_8_vaṃ.JPG",
        "year": 1340
      },
      {
        "id": 5,
        "form": "vaṃ_form1",
        "path": "vaṃ/vaṃ_form1/1340_Bn111_Ramasamudra_44_18_vaṃ.JPG",
        "year": 1340
      },
      {
        "id": 6,
        "form": "vaṃ_form1",
        "path": "vaṃ/vaṃ_form1/1340_Bn111_Ramasamudra_47_5_vaṃ.JPG",
        "year": 1340
      },
      {
        "id": 7,
        "form": "vaṃ_form2",
        "path": "vaṃ/vaṃ_form2/1329_IthDar_Kadatanamale_18_9_vaṃ.JPG",
        "year": 1329
      },
      {
        "id": 8,
        "form": "vaṃ_form2",
        "path": "vaṃ/vaṃ_form2/1336_Bn110_Byadarahalli_17_9_vaṃ.JPG",
        "year": 1336
      },
      {
        "id": 9,
        "form": "vaṃ_form2",
        "path": "vaṃ/vaṃ_form2/1336_Bn110_Byadarahalli_23_12_vaṃ.JPG",
        "year": 1336
      },
      {
        "id": 10,
        "form": "vaṃ_form2",
        "path": "vaṃ/vaṃ_form2/1363_BN81_AgaraMuseum_15_12_vaṃ.JPG",
        "year": 1363
      },
      {
        "id": 11,
        "form": "vaṃ_form2",
        "path": "vaṃ/vaṃ_form2/1369_CP150_Malurpatna_4_11_vaṃ.JPG",
        "year": 1369
      }
    ],
    "IASTform": ""
  }
]