[
  {
    "id": 1,
    "year": 1700,
    "encoding": "BN167",
    "place": "Kalkere",
    "lineNumber": 2,
    "posNumber": 2,
    "letter": "1",
    "fileName": "1700_BN167_Kalkere_2_2_1",
    "filePath": "1/1_form1/1700_BN167_Kalkere_2_2_1.png",
    "kannadaWord": "1"
  },
  {
    "id": 2,
    "year": 1700,
    "encoding": "BN167",
    "place": "Kalkere",
    "lineNumber": 10,
    "posNumber": 14,
    "letter": "ba",
    "fileName": "1700_BN167_Kalkere_10_14_ba",
    "filePath": "ba/ba_form1/1700_BN167_Kalkere_10_14_ba.png",
    "kannadaWord": "ಬ"
  },
  {
    "id": 3,
    "year": 1700,
    "encoding": "BN167",
    "place": "Kalkere",
    "lineNumber": 9,
    "posNumber": 21,
    "letter": "be",
    "fileName": "1700_BN167_Kalkere_9_21_be",
    "filePath": "be/be_form1/1700_BN167_Kalkere_9_21_be.png",
    "kannadaWord": "ಬೇ"
  },
  {
    "id": 4,
    "year": 1700,
    "encoding": "BN167",
    "place": "Kalkere",
    "lineNumber": 10,
    "posNumber": 3,
    "letter": "bi",
    "fileName": "1700_BN167_Kalkere_10_3_bi",
    "filePath": "bi/bi_form1/1700_BN167_Kalkere_10_3_bi.png",
    "kannadaWord": "ಬಿ"
  },
  {
    "id": 5,
    "year": 1700,
    "encoding": "BN167",
    "place": "Kalkere",
    "lineNumber": 1,
    "posNumber": 9,
    "letter": "ca",
    "fileName": "1700_BN167_Kalkere_1_9_ca",
    "filePath": "ca/ca_form1/1700_BN167_Kalkere_1_9_ca.png",
    "kannadaWord": "ಚ"
  },
  {
    "id": 6,
    "year": 1700,
    "encoding": "BN167",
    "place": "Kalkere",
    "lineNumber": 6,
    "posNumber": 7,
    "letter": "ci",
    "fileName": "1700_BN167_Kalkere_6_7_ci",
    "filePath": "ci/ci_form1/1700_BN167_Kalkere_6_7_ci.png",
    "kannadaWord": "ಚಿ"
  },
  {
    "id": 7,
    "year": 1700,
    "encoding": "BN167",
    "place": "Kalkere",
    "lineNumber": 4,
    "posNumber": 1,
    "letter": "cŏ",
    "fileName": "1700_BN167_Kalkere_4_1_cŏ",
    "filePath": "cŏ/cŏ_form1/1700_BN167_Kalkere_4_1_cŏ.png",
    "kannadaWord": "ಚೊ"
  },
  {
    "id": 8,
    "year": 1700,
    "encoding": "BN167",
    "place": "Kalkere",
    "lineNumber": 10,
    "posNumber": 8,
    "letter": "da",
    "fileName": "1700_BN167_Kalkere_10_8_da",
    "filePath": "da/da_form1/1700_BN167_Kalkere_10_8_da.png",
    "kannadaWord": "ದ"
  },
  {
    "id": 9,
    "year": 1700,
    "encoding": "BN167",
    "place": "Kalkere",
    "lineNumber": 1,
    "posNumber": 8,
    "letter": "da",
    "fileName": "1700_BN167_Kalkere_1_8_da",
    "filePath": "da/da_form1/1700_BN167_Kalkere_1_8_da.png",
    "kannadaWord": "ದ"
  },
  {
    "id": 10,
    "year": 1700,
    "encoding": "BN167",
    "place": "Kalkere",
    "lineNumber": 2,
    "posNumber": 4,
    "letter": "da",
    "fileName": "1700_BN167_Kalkere_2_4_da",
    "filePath": "da/da_form1/1700_BN167_Kalkere_2_4_da.png",
    "kannadaWord": "ದ"
  },
  {
    "id": 11,
    "year": 1700,
    "encoding": "BN167",
    "place": "Kalkere",
    "lineNumber": 5,
    "posNumber": 8,
    "letter": "da",
    "fileName": "1700_BN167_Kalkere_5_8_da",
    "filePath": "da/da_form1/1700_BN167_Kalkere_5_8_da.png",
    "kannadaWord": "ದ"
  },
  {
    "id": 12,
    "year": 1700,
    "encoding": "BN167",
    "place": "Kalkere",
    "lineNumber": 9,
    "posNumber": 17,
    "letter": "dha",
    "fileName": "1700_BN167_Kalkere_9_17_dha",
    "filePath": "dha/dha_form1/1700_BN167_Kalkere_9_17_dha.png",
    "kannadaWord": "ಧ"
  },
  {
    "id": 13,
    "year": 1700,
    "encoding": "BN167",
    "place": "Kalkere",
    "lineNumber": 9,
    "posNumber": 23,
    "letter": "du",
    "fileName": "1700_BN167_Kalkere_9_23_du",
    "filePath": "du/du_form1/1700_BN167_Kalkere_9_23_du.png",
    "kannadaWord": "ದು"
  },
  {
    "id": 14,
    "year": 1700,
    "encoding": "BN167",
    "place": "Kalkere",
    "lineNumber": 4,
    "posNumber": 10,
    "letter": "ga",
    "fileName": "1700_BN167_Kalkere_4_10_ga",
    "filePath": "ga/ga_form1/1700_BN167_Kalkere_4_10_ga.png",
    "kannadaWord": "ಗ"
  },
  {
    "id": 15,
    "year": 1700,
    "encoding": "BN167",
    "place": "Kalkere",
    "lineNumber": 9,
    "posNumber": 20,
    "letter": "ga",
    "fileName": "1700_BN167_Kalkere_9_20_ga",
    "filePath": "ga/ga_form1/1700_BN167_Kalkere_9_20_ga.png",
    "kannadaWord": "ಗ"
  },
  {
    "id": 16,
    "year": 1700,
    "encoding": "BN167",
    "place": "Kalkere",
    "lineNumber": 11,
    "posNumber": 7,
    "letter": "gaṃ",
    "fileName": "1700_BN167_Kalkere_11_7_gaṃ",
    "filePath": "gaṃ/gaṃ_form1/1700_BN167_Kalkere_11_7_gaṃ.png",
    "kannadaWord": "ಗಂ"
  },
  {
    "id": 17,
    "year": 1700,
    "encoding": "BN167",
    "place": "Kalkere",
    "lineNumber": 11,
    "posNumber": 14,
    "letter": "gĕ",
    "fileName": "1700_BN167_Kalkere_11_14_gĕ",
    "filePath": "gĕ/gĕ_form1/1700_BN167_Kalkere_11_14_gĕ.png",
    "kannadaWord": "ಗೆ"
  },
  {
    "id": 18,
    "year": 1700,
    "encoding": "BN167",
    "place": "Kalkere",
    "lineNumber": 11,
    "posNumber": 8,
    "letter": "gĕ",
    "fileName": "1700_BN167_Kalkere_11_8_gĕ",
    "filePath": "gĕ/gĕ_form1/1700_BN167_Kalkere_11_8_gĕ.png",
    "kannadaWord": "ಗೆ"
  },
  {
    "id": 19,
    "year": 1700,
    "encoding": "BN167",
    "place": "Kalkere",
    "lineNumber": 3,
    "posNumber": 13,
    "letter": "gĕ",
    "fileName": "1700_BN167_Kalkere_3_13_gĕ",
    "filePath": "gĕ/gĕ_form1/1700_BN167_Kalkere_3_13_gĕ.png",
    "kannadaWord": "ಗೆ"
  },
  {
    "id": 20,
    "year": 1700,
    "encoding": "BN167",
    "place": "Kalkere",
    "lineNumber": 8,
    "posNumber": 7,
    "letter": "gĕ",
    "fileName": "1700_BN167_Kalkere_8_7_gĕ",
    "filePath": "gĕ/gĕ_form1/1700_BN167_Kalkere_8_7_gĕ.png",
    "kannadaWord": "ಗೆ"
  },
  {
    "id": 21,
    "year": 1700,
    "encoding": "BN167",
    "place": "Kalkere",
    "lineNumber": 9,
    "posNumber": 16,
    "letter": "gĕ",
    "fileName": "1700_BN167_Kalkere_9_16_gĕ",
    "filePath": "gĕ/gĕ_form1/1700_BN167_Kalkere_9_16_gĕ.png",
    "kannadaWord": "ಗೆ"
  },
  {
    "id": 22,
    "year": 1700,
    "encoding": "BN167",
    "place": "Kalkere",
    "lineNumber": 12,
    "posNumber": 14,
    "letter": "ha",
    "fileName": "1700_BN167_Kalkere_12_14_ha",
    "filePath": "ha/ha_form1/1700_BN167_Kalkere_12_14_ha.png",
    "kannadaWord": "ಹ"
  },
  {
    "id": 23,
    "year": 1700,
    "encoding": "BN167",
    "place": "Kalkere",
    "lineNumber": 5,
    "posNumber": 13,
    "letter": "hi",
    "fileName": "1700_BN167_Kalkere_5_13_hi",
    "filePath": "hi/hi_form1/1700_BN167_Kalkere_5_13_hi.png",
    "kannadaWord": "ಹಿ"
  },
  {
    "id": 24,
    "year": 1700,
    "encoding": "BN167",
    "place": "Kalkere",
    "lineNumber": 12,
    "posNumber": 13,
    "letter": "ho",
    "fileName": "1700_BN167_Kalkere_12_13_ho",
    "filePath": "ho/ho_form1/1700_BN167_Kalkere_12_13_ho.png",
    "kannadaWord": "ಹೋ"
  },
  {
    "id": 25,
    "year": 1700,
    "encoding": "BN167",
    "place": "Kalkere",
    "lineNumber": 1,
    "posNumber": 3,
    "letter": "ka",
    "fileName": "1700_BN167_Kalkere_1_3_ka",
    "filePath": "ka/ka_form1/1700_BN167_Kalkere_1_3_ka.png",
    "kannadaWord": "ಕ"
  },
  {
    "id": 26,
    "year": 1700,
    "encoding": "BN167",
    "place": "Kalkere",
    "lineNumber": 3,
    "posNumber": 2,
    "letter": "ka",
    "fileName": "1700_BN167_Kalkere_3_2_ka",
    "filePath": "ka/ka_form1/1700_BN167_Kalkere_3_2_ka.png",
    "kannadaWord": "ಕ"
  },
  {
    "id": 27,
    "year": 1700,
    "encoding": "BN167",
    "place": "Kalkere",
    "lineNumber": 3,
    "posNumber": 4,
    "letter": "ka",
    "fileName": "1700_BN167_Kalkere_3_4_ka",
    "filePath": "ka/ka_form1/1700_BN167_Kalkere_3_4_ka.png",
    "kannadaWord": "ಕ"
  },
  {
    "id": 28,
    "year": 1700,
    "encoding": "BN167",
    "place": "Kalkere",
    "lineNumber": 5,
    "posNumber": 5,
    "letter": "ka",
    "fileName": "1700_BN167_Kalkere_5_5_ka",
    "filePath": "ka/ka_form1/1700_BN167_Kalkere_5_5_ka.png",
    "kannadaWord": "ಕ"
  },
  {
    "id": 29,
    "year": 1700,
    "encoding": "BN167",
    "place": "Kalkere",
    "lineNumber": 6,
    "posNumber": 8,
    "letter": "kka",
    "fileName": "1700_BN167_Kalkere_6_8_kka",
    "filePath": "kka/kka_form1/1700_BN167_Kalkere_6_8_kka.png",
    "kannadaWord": "ಕ್ಕ"
  },
  {
    "id": 30,
    "year": 1700,
    "encoding": "BN167",
    "place": "Kalkere",
    "lineNumber": 4,
    "posNumber": 2,
    "letter": "kki",
    "fileName": "1700_BN167_Kalkere_4_2_kki",
    "filePath": "kki/kki_form1/1700_BN167_Kalkere_4_2_kki.png",
    "kannadaWord": "ಕ್ಕಿ"
  },
  {
    "id": 31,
    "year": 1700,
    "encoding": "BN167",
    "place": "Kalkere",
    "lineNumber": 10,
    "posNumber": 9,
    "letter": "kkĕ",
    "fileName": "1700_BN167_Kalkere_10_9_kkĕ",
    "filePath": "kkĕ/kkĕ_form1/1700_BN167_Kalkere_10_9_kkĕ.png",
    "kannadaWord": "ಕ್ಕೆ"
  },
  {
    "id": 32,
    "year": 1700,
    "encoding": "BN167",
    "place": "Kalkere",
    "lineNumber": 3,
    "posNumber": 6,
    "letter": "kĕ",
    "fileName": "1700_BN167_Kalkere_3_6_kĕ",
    "filePath": "kĕ/kĕ_form1/1700_BN167_Kalkere_3_6_kĕ.png",
    "kannadaWord": "ಕೆ"
  },
  {
    "id": 33,
    "year": 1700,
    "encoding": "BN167",
    "place": "Kalkere",
    "lineNumber": 4,
    "posNumber": 6,
    "letter": "kĕ",
    "fileName": "1700_BN167_Kalkere_4_6_kĕ",
    "filePath": "kĕ/kĕ_form1/1700_BN167_Kalkere_4_6_kĕ.png",
    "kannadaWord": "ಕೆ"
  },
  {
    "id": 34,
    "year": 1700,
    "encoding": "BN167",
    "place": "Kalkere",
    "lineNumber": 5,
    "posNumber": 9,
    "letter": "kĕ",
    "fileName": "1700_BN167_Kalkere_5_9_kĕ",
    "filePath": "kĕ/kĕ_form1/1700_BN167_Kalkere_5_9_kĕ.png",
    "kannadaWord": "ಕೆ"
  },
  {
    "id": 35,
    "year": 1700,
    "encoding": "BN167",
    "place": "Kalkere",
    "lineNumber": 9,
    "posNumber": 22,
    "letter": "kĕṃ",
    "fileName": "1700_BN167_Kalkere_9_22_kĕṃ",
    "filePath": "kĕṃ/kĕṃ_form1/1700_BN167_Kalkere_9_22_kĕṃ.png",
    "kannadaWord": "ಕೆಂ"
  },
  {
    "id": 36,
    "year": 1700,
    "encoding": "BN167",
    "place": "Kalkere",
    "lineNumber": 1,
    "posNumber": 1,
    "letter": "kī",
    "fileName": "1700_BN167_Kalkere_1_1_kī",
    "filePath": "kī/kī_form1/1700_BN167_Kalkere_1_1_kī.png",
    "kannadaWord": "ಕೀ"
  },
  {
    "id": 37,
    "year": 1700,
    "encoding": "BN167",
    "place": "Kalkere",
    "lineNumber": 1,
    "posNumber": 2,
    "letter": "la",
    "fileName": "1700_BN167_Kalkere_1_2_la",
    "filePath": "la/la_form1/1700_BN167_Kalkere_1_2_la.png",
    "kannadaWord": "ಲ"
  },
  {
    "id": 38,
    "year": 1700,
    "encoding": "BN167",
    "place": "Kalkere",
    "lineNumber": 12,
    "posNumber": 12,
    "letter": "li",
    "fileName": "1700_BN167_Kalkere_12_12_li",
    "filePath": "li/li_form1/1700_BN167_Kalkere_12_12_li.png",
    "kannadaWord": "ಲಿ"
  },
  {
    "id": 39,
    "year": 1700,
    "encoding": "BN167",
    "place": "Kalkere",
    "lineNumber": 7,
    "posNumber": 1,
    "letter": "lla",
    "fileName": "1700_BN167_Kalkere_7_1_lla",
    "filePath": "lla/lla_form1/1700_BN167_Kalkere_7_1_lla.png",
    "kannadaWord": "ಲ್ಲ"
  },
  {
    "id": 40,
    "year": 1700,
    "encoding": "BN167",
    "place": "Kalkere",
    "lineNumber": 2,
    "posNumber": 3,
    "letter": "lu",
    "fileName": "1700_BN167_Kalkere_2_3_lu",
    "filePath": "lu/lu_form1/1700_BN167_Kalkere_2_3_lu.png",
    "kannadaWord": "ಲು"
  },
  {
    "id": 41,
    "year": 1700,
    "encoding": "BN167",
    "place": "Kalkere",
    "lineNumber": 3,
    "posNumber": 5,
    "letter": "lu",
    "fileName": "1700_BN167_Kalkere_3_5_lu",
    "filePath": "lu/lu_form1/1700_BN167_Kalkere_3_5_lu.png",
    "kannadaWord": "ಲು"
  },
  {
    "id": 42,
    "year": 1700,
    "encoding": "BN167",
    "place": "Kalkere",
    "lineNumber": 2,
    "posNumber": 9,
    "letter": "lĕ",
    "fileName": "1700_BN167_Kalkere_2_9_lĕ",
    "filePath": "lĕ/lĕ_form1/1700_BN167_Kalkere_2_9_lĕ.png",
    "kannadaWord": "ಲೆ"
  },
  {
    "id": 43,
    "year": 1700,
    "encoding": "BN167",
    "place": "Kalkere",
    "lineNumber": 2,
    "posNumber": 5,
    "letter": "l̤a",
    "fileName": "1700_BN167_Kalkere_2_5_l̤a",
    "filePath": "l̤a/l̤a_form1/1700_BN167_Kalkere_2_5_l̤a.png",
    "kannadaWord": "ಳ"
  },
  {
    "id": 44,
    "year": 1700,
    "encoding": "BN167",
    "place": "Kalkere",
    "lineNumber": 3,
    "posNumber": 12,
    "letter": "l̤a",
    "fileName": "1700_BN167_Kalkere_3_12_l̤a",
    "filePath": "l̤a/l̤a_form1/1700_BN167_Kalkere_3_12_l̤a.png",
    "kannadaWord": "ಳ"
  },
  {
    "id": 45,
    "year": 1700,
    "encoding": "BN167",
    "place": "Kalkere",
    "lineNumber": 11,
    "posNumber": 15,
    "letter": "l̤u",
    "fileName": "1700_BN167_Kalkere_11_15_l̤u",
    "filePath": "l̤u/l̤u_form1/1700_BN167_Kalkere_11_15_l̤u.png",
    "kannadaWord": "ಳು"
  },
  {
    "id": 46,
    "year": 1700,
    "encoding": "BN167",
    "place": "Kalkere",
    "lineNumber": 6,
    "posNumber": 13,
    "letter": "ma",
    "fileName": "1700_BN167_Kalkere_6_13_ma",
    "filePath": "ma/ma_form1/1700_BN167_Kalkere_6_13_ma.png",
    "kannadaWord": "ಮ"
  },
  {
    "id": 47,
    "year": 1700,
    "encoding": "BN167",
    "place": "Kalkere",
    "lineNumber": 8,
    "posNumber": 9,
    "letter": "ma",
    "fileName": "1700_BN167_Kalkere_8_9_ma",
    "filePath": "ma/ma_form1/1700_BN167_Kalkere_8_9_ma.png",
    "kannadaWord": "ಮ"
  },
  {
    "id": 48,
    "year": 1700,
    "encoding": "BN167",
    "place": "Kalkere",
    "lineNumber": 4,
    "posNumber": 9,
    "letter": "me",
    "fileName": "1700_BN167_Kalkere_4_9_me",
    "filePath": "me/me_form1/1700_BN167_Kalkere_4_9_me.png",
    "kannadaWord": "ಮೇ"
  },
  {
    "id": 49,
    "year": 1700,
    "encoding": "BN167",
    "place": "Kalkere",
    "lineNumber": 3,
    "posNumber": 10,
    "letter": "mĕ",
    "fileName": "1700_BN167_Kalkere_3_10_mĕ",
    "filePath": "mĕ/mĕ_form1/1700_BN167_Kalkere_3_10_mĕ.png",
    "kannadaWord": "ಮೆ"
  },
  {
    "id": 50,
    "year": 1700,
    "encoding": "BN167",
    "place": "Kalkere",
    "lineNumber": 4,
    "posNumber": 13,
    "letter": "mĕ",
    "fileName": "1700_BN167_Kalkere_4_13_mĕ",
    "filePath": "mĕ/mĕ_form1/1700_BN167_Kalkere_4_13_mĕ.png",
    "kannadaWord": "ಮೆ"
  },
  {
    "id": 51,
    "year": 1700,
    "encoding": "BN167",
    "place": "Kalkere",
    "lineNumber": 7,
    "posNumber": 8,
    "letter": "mū",
    "fileName": "1700_BN167_Kalkere_7_8_mū",
    "filePath": "mū/mū_form1/1700_BN167_Kalkere_7_8_mū.png",
    "kannadaWord": "ಮೂ"
  },
  {
    "id": 52,
    "year": 1700,
    "encoding": "BN167",
    "place": "Kalkere",
    "lineNumber": 5,
    "posNumber": 12,
    "letter": "nu",
    "fileName": "1700_BN167_Kalkere_5_12_nu",
    "filePath": "nu/nu_form1/1700_BN167_Kalkere_5_12_nu.png",
    "kannadaWord": "ನು"
  },
  {
    "id": 53,
    "year": 1700,
    "encoding": "BN167",
    "place": "Kalkere",
    "lineNumber": 5,
    "posNumber": 2,
    "letter": "nu",
    "fileName": "1700_BN167_Kalkere_5_2_nu",
    "filePath": "nu/nu_form1/1700_BN167_Kalkere_5_2_nu.png",
    "kannadaWord": "ನು"
  },
  {
    "id": 54,
    "year": 1700,
    "encoding": "BN167",
    "place": "Kalkere",
    "lineNumber": 10,
    "posNumber": 12,
    "letter": "nā",
    "fileName": "1700_BN167_Kalkere_10_12_nā",
    "filePath": "nā/nā_form1/1700_BN167_Kalkere_10_12_nā.png",
    "kannadaWord": "ನಾ"
  },
  {
    "id": 55,
    "year": 1700,
    "encoding": "BN167",
    "place": "Kalkere",
    "lineNumber": 10,
    "posNumber": 1,
    "letter": "nā",
    "fileName": "1700_BN167_Kalkere_10_1_nā",
    "filePath": "nā/nā_form1/1700_BN167_Kalkere_10_1_nā.png",
    "kannadaWord": "ನಾ"
  },
  {
    "id": 56,
    "year": 1700,
    "encoding": "BN167",
    "place": "Kalkere",
    "lineNumber": 2,
    "posNumber": 11,
    "letter": "nā",
    "fileName": "1700_BN167_Kalkere_2_11_nā",
    "filePath": "nā/nā_form1/1700_BN167_Kalkere_2_11_nā.png",
    "kannadaWord": "ನಾ"
  },
  {
    "id": 57,
    "year": 1700,
    "encoding": "BN167",
    "place": "Kalkere",
    "lineNumber": 5,
    "posNumber": 3,
    "letter": "nā",
    "fileName": "1700_BN167_Kalkere_5_3_nā",
    "filePath": "nā/nā_form1/1700_BN167_Kalkere_5_3_nā.png",
    "kannadaWord": "ನಾ"
  },
  {
    "id": 58,
    "year": 1700,
    "encoding": "BN167",
    "place": "Kalkere",
    "lineNumber": 10,
    "posNumber": 13,
    "letter": "nŏ",
    "fileName": "1700_BN167_Kalkere_10_13_nŏ",
    "filePath": "nŏ/nŏ_form1/1700_BN167_Kalkere_10_13_nŏ.png",
    "kannadaWord": "ನೊ"
  },
  {
    "id": 59,
    "year": 1700,
    "encoding": "BN167",
    "place": "Kalkere",
    "lineNumber": 10,
    "posNumber": 15,
    "letter": "nŏ",
    "fileName": "1700_BN167_Kalkere_10_15_nŏ",
    "filePath": "nŏ/nŏ_form1/1700_BN167_Kalkere_10_15_nŏ.png",
    "kannadaWord": "ನೊ"
  },
  {
    "id": 60,
    "year": 1700,
    "encoding": "BN167",
    "place": "Kalkere",
    "lineNumber": 10,
    "posNumber": 5,
    "letter": "pu",
    "fileName": "1700_BN167_Kalkere_10_5_pu",
    "filePath": "pu/pu_form1/1700_BN167_Kalkere_10_5_pu.png",
    "kannadaWord": "ಪು"
  },
  {
    "id": 61,
    "year": 1700,
    "encoding": "BN167",
    "place": "Kalkere",
    "lineNumber": 10,
    "posNumber": 6,
    "letter": "ra",
    "fileName": "1700_BN167_Kalkere_10_6_ra",
    "filePath": "ra/ra_form1/1700_BN167_Kalkere_10_6_ra.png",
    "kannadaWord": "ರ"
  },
  {
    "id": 62,
    "year": 1700,
    "encoding": "BN167",
    "place": "Kalkere",
    "lineNumber": 1,
    "posNumber": 7,
    "letter": "ra",
    "fileName": "1700_BN167_Kalkere_1_7_ra",
    "filePath": "ra/ra_form1/1700_BN167_Kalkere_1_7_ra.png",
    "kannadaWord": "ರ"
  },
  {
    "id": 63,
    "year": 1700,
    "encoding": "BN167",
    "place": "Kalkere",
    "lineNumber": 8,
    "posNumber": 10,
    "letter": "ra",
    "fileName": "1700_BN167_Kalkere_8_10_ra",
    "filePath": "ra/ra_form1/1700_BN167_Kalkere_8_10_ra.png",
    "kannadaWord": "ರ"
  },
  {
    "id": 64,
    "year": 1700,
    "encoding": "BN167",
    "place": "Kalkere",
    "lineNumber": 8,
    "posNumber": 4,
    "letter": "ra",
    "fileName": "1700_BN167_Kalkere_8_4_ra",
    "filePath": "ra/ra_form1/1700_BN167_Kalkere_8_4_ra.png",
    "kannadaWord": "ರ"
  },
  {
    "id": 65,
    "year": 1700,
    "encoding": "BN167",
    "place": "Kalkere",
    "lineNumber": 6,
    "posNumber": 1,
    "letter": "ri",
    "fileName": "1700_BN167_Kalkere_6_1_ri",
    "filePath": "ri/ri_form1/1700_BN167_Kalkere_6_1_ri.png",
    "kannadaWord": "ರಿ"
  },
  {
    "id": 66,
    "year": 1700,
    "encoding": "BN167",
    "place": "Kalkere",
    "lineNumber": 8,
    "posNumber": 6,
    "letter": "ri",
    "fileName": "1700_BN167_Kalkere_8_6_ri",
    "filePath": "ri/ri_form2/1700_BN167_Kalkere_8_6_ri.png",
    "kannadaWord": "ರಿ"
  },
  {
    "id": 67,
    "year": 1700,
    "encoding": "BN167",
    "place": "Kalkere",
    "lineNumber": 9,
    "posNumber": 15,
    "letter": "ri",
    "fileName": "1700_BN167_Kalkere_9_15_ri",
    "filePath": "ri/ri_form2/1700_BN167_Kalkere_9_15_ri.png",
    "kannadaWord": "ರಿ"
  },
  {
    "id": 68,
    "year": 1700,
    "encoding": "BN167",
    "place": "Kalkere",
    "lineNumber": 9,
    "posNumber": 18,
    "letter": "rma",
    "fileName": "1700_BN167_Kalkere_9_18_rma",
    "filePath": "rma/rma_form1/1700_BN167_Kalkere_9_18_rma.png",
    "kannadaWord": "ರ್ಮ"
  },
  {
    "id": 69,
    "year": 1700,
    "encoding": "BN167",
    "place": "Kalkere",
    "lineNumber": 11,
    "posNumber": 6,
    "letter": "ru",
    "fileName": "1700_BN167_Kalkere_11_6_ru",
    "filePath": "ru/ru_form1/1700_BN167_Kalkere_11_6_ru.png",
    "kannadaWord": "ರು"
  },
  {
    "id": 70,
    "year": 1700,
    "encoding": "BN167",
    "place": "Kalkere",
    "lineNumber": 12,
    "posNumber": 15,
    "letter": "ru",
    "fileName": "1700_BN167_Kalkere_12_15_ru",
    "filePath": "ru/ru_form1/1700_BN167_Kalkere_12_15_ru.png",
    "kannadaWord": "ರು"
  },
  {
    "id": 71,
    "year": 1700,
    "encoding": "BN167",
    "place": "Kalkere",
    "lineNumber": 3,
    "posNumber": 3,
    "letter": "ru",
    "fileName": "1700_BN167_Kalkere_3_3_ru",
    "filePath": "ru/ru_form1/1700_BN167_Kalkere_3_3_ru.png",
    "kannadaWord": "ರು"
  },
  {
    "id": 72,
    "year": 1700,
    "encoding": "BN167",
    "place": "Kalkere",
    "lineNumber": 6,
    "posNumber": 12,
    "letter": "ru",
    "fileName": "1700_BN167_Kalkere_6_12_ru",
    "filePath": "ru/ru_form1/1700_BN167_Kalkere_6_12_ru.png",
    "kannadaWord": "ರು"
  },
  {
    "id": 73,
    "year": 1700,
    "encoding": "BN167",
    "place": "Kalkere",
    "lineNumber": 6,
    "posNumber": 6,
    "letter": "ru",
    "fileName": "1700_BN167_Kalkere_6_6_ru",
    "filePath": "ru/ru_form1/1700_BN167_Kalkere_6_6_ru.png",
    "kannadaWord": "ರು"
  },
  {
    "id": 74,
    "year": 1700,
    "encoding": "BN167",
    "place": "Kalkere",
    "lineNumber": 7,
    "posNumber": 10,
    "letter": "ru",
    "fileName": "1700_BN167_Kalkere_7_10_ru",
    "filePath": "ru/ru_form1/1700_BN167_Kalkere_7_10_ru.png",
    "kannadaWord": "ರು"
  },
  {
    "id": 75,
    "year": 1700,
    "encoding": "BN167",
    "place": "Kalkere",
    "lineNumber": 7,
    "posNumber": 6,
    "letter": "ru",
    "fileName": "1700_BN167_Kalkere_7_6_ru",
    "filePath": "ru/ru_form1/1700_BN167_Kalkere_7_6_ru.png",
    "kannadaWord": "ರು"
  },
  {
    "id": 76,
    "year": 1700,
    "encoding": "BN167",
    "place": "Kalkere",
    "lineNumber": 8,
    "posNumber": 11,
    "letter": "sa",
    "fileName": "1700_BN167_Kalkere_8_11_sa",
    "filePath": "sa/sa_form2/1700_BN167_Kalkere_8_11_sa.png",
    "kannadaWord": "ಸ"
  },
  {
    "id": 77,
    "year": 1700,
    "encoding": "BN167",
    "place": "Kalkere",
    "lineNumber": 1,
    "posNumber": 4,
    "letter": "saṃ",
    "fileName": "1700_BN167_Kalkere_1_4_saṃ",
    "filePath": "saṃ/saṃ_form2/1700_BN167_Kalkere_1_4_saṃ.png",
    "kannadaWord": "ಸಂ"
  },
  {
    "id": 78,
    "year": 1700,
    "encoding": "BN167",
    "place": "Kalkere",
    "lineNumber": 5,
    "posNumber": 7,
    "letter": "si",
    "fileName": "1700_BN167_Kalkere_5_7_si",
    "filePath": "si/si_form1/1700_BN167_Kalkere_5_7_si.png",
    "kannadaWord": "ಸಿ"
  },
  {
    "id": 79,
    "year": 1700,
    "encoding": "BN167",
    "place": "Kalkere",
    "lineNumber": 2,
    "posNumber": 1,
    "letter": "su",
    "fileName": "1700_BN167_Kalkere_2_1_su",
    "filePath": "su/su_form1/1700_BN167_Kalkere_2_1_su.png",
    "kannadaWord": "ಸು"
  },
  {
    "id": 80,
    "year": 1700,
    "encoding": "BN167",
    "place": "Kalkere",
    "lineNumber": 4,
    "posNumber": 3,
    "letter": "sĕ",
    "fileName": "1700_BN167_Kalkere_4_3_sĕ",
    "filePath": "sĕ/sĕ_form1/1700_BN167_Kalkere_4_3_sĕ.png",
    "kannadaWord": "ಸೆ"
  },
  {
    "id": 81,
    "year": 1700,
    "encoding": "BN167",
    "place": "Kalkere",
    "lineNumber": 3,
    "posNumber": 9,
    "letter": "sī",
    "fileName": "1700_BN167_Kalkere_3_9_sī",
    "filePath": "sī/sī_form1/1700_BN167_Kalkere_3_9_sī.png",
    "kannadaWord": "ಸೀ"
  },
  {
    "id": 82,
    "year": 1700,
    "encoding": "BN167",
    "place": "Kalkere",
    "lineNumber": 4,
    "posNumber": 12,
    "letter": "sī",
    "fileName": "1700_BN167_Kalkere_4_12_sī",
    "filePath": "sī/sī_form2/1700_BN167_Kalkere_4_12_sī.png",
    "kannadaWord": "ಸೀ"
  },
  {
    "id": 83,
    "year": 1700,
    "encoding": "BN167",
    "place": "Kalkere",
    "lineNumber": 11,
    "posNumber": 10,
    "letter": "ta",
    "fileName": "1700_BN167_Kalkere_11_10_ta",
    "filePath": "ta/ta_form1/1700_BN167_Kalkere_11_10_ta.png",
    "kannadaWord": "ತ"
  },
  {
    "id": 84,
    "year": 1700,
    "encoding": "BN167",
    "place": "Kalkere",
    "lineNumber": 11,
    "posNumber": 13,
    "letter": "taṃ",
    "fileName": "1700_BN167_Kalkere_11_13_taṃ",
    "filePath": "taṃ/taṃ_form1/1700_BN167_Kalkere_11_13_taṃ.png",
    "kannadaWord": "ತಂ"
  },
  {
    "id": 85,
    "year": 1700,
    "encoding": "BN167",
    "place": "Kalkere",
    "lineNumber": 8,
    "posNumber": 8,
    "letter": "tiṃ",
    "fileName": "1700_BN167_Kalkere_8_8_tiṃ",
    "filePath": "tiṃ/tiṃ_form1/1700_BN167_Kalkere_8_8_tiṃ.png",
    "kannadaWord": "ತಿಂ"
  },
  {
    "id": 86,
    "year": 1700,
    "encoding": "BN167",
    "place": "Kalkere",
    "lineNumber": 1,
    "posNumber": 11,
    "letter": "tra",
    "fileName": "1700_BN167_Kalkere_1_11_tra",
    "filePath": "tra/tra_form2/1700_BN167_Kalkere_1_11_tra.png",
    "kannadaWord": "ತ್ರ"
  },
  {
    "id": 87,
    "year": 1700,
    "encoding": "BN167",
    "place": "Kalkere",
    "lineNumber": 1,
    "posNumber": 6,
    "letter": "tsa",
    "fileName": "1700_BN167_Kalkere_1_6_tsa",
    "filePath": "tsa/tsa_form1/1700_BN167_Kalkere_1_6_tsa.png",
    "kannadaWord": ""
  },
  {
    "id": 88,
    "year": 1700,
    "encoding": "BN167",
    "place": "Kalkere",
    "lineNumber": 10,
    "posNumber": 2,
    "letter": "u",
    "fileName": "1700_BN167_Kalkere_10_2_u",
    "filePath": "u/u_form1/1700_BN167_Kalkere_10_2_u.png",
    "kannadaWord": "ಉ"
  },
  {
    "id": 89,
    "year": 1700,
    "encoding": "BN167",
    "place": "Kalkere",
    "lineNumber": 5,
    "posNumber": 4,
    "letter": "u",
    "fileName": "1700_BN167_Kalkere_5_4_u",
    "filePath": "u/u_form1/1700_BN167_Kalkere_5_4_u.png",
    "kannadaWord": "ಉ"
  },
  {
    "id": 90,
    "year": 1700,
    "encoding": "BN167",
    "place": "Kalkere",
    "lineNumber": 1,
    "posNumber": 5,
    "letter": "va",
    "fileName": "1700_BN167_Kalkere_1_5_va",
    "filePath": "va/va_form1/1700_BN167_Kalkere_1_5_va.png",
    "kannadaWord": "ವ"
  },
  {
    "id": 91,
    "year": 1700,
    "encoding": "BN167",
    "place": "Kalkere",
    "lineNumber": 7,
    "posNumber": 9,
    "letter": "va",
    "fileName": "1700_BN167_Kalkere_7_9_va",
    "filePath": "va/va_form1/1700_BN167_Kalkere_7_9_va.png",
    "kannadaWord": "ವ"
  },
  {
    "id": 92,
    "year": 1700,
    "encoding": "BN167",
    "place": "Kalkere",
    "lineNumber": 10,
    "posNumber": 11,
    "letter": "va",
    "fileName": "1700_BN167_Kalkere_10_11_va",
    "filePath": "va/va_form2/1700_BN167_Kalkere_10_11_va.png",
    "kannadaWord": "ವ"
  },
  {
    "id": 93,
    "year": 1700,
    "encoding": "BN167",
    "place": "Kalkere",
    "lineNumber": 8,
    "posNumber": 5,
    "letter": "va",
    "fileName": "1700_BN167_Kalkere_8_5_va",
    "filePath": "va/va_form2/1700_BN167_Kalkere_8_5_va.png",
    "kannadaWord": "ವ"
  },
  {
    "id": 94,
    "year": 1700,
    "encoding": "BN167",
    "place": "Kalkere",
    "lineNumber": 2,
    "posNumber": 6,
    "letter": "vā",
    "fileName": "1700_BN167_Kalkere_2_6_vā",
    "filePath": "vā/vā_form2/1700_BN167_Kalkere_2_6_vā.png",
    "kannadaWord": "ವಾ"
  },
  {
    "id": 95,
    "year": 1700,
    "encoding": "BN167",
    "place": "Kalkere",
    "lineNumber": 9,
    "posNumber": 19,
    "letter": "vā",
    "fileName": "1700_BN167_Kalkere_9_19_vā",
    "filePath": "vā/vā_form2/1700_BN167_Kalkere_9_19_vā.png",
    "kannadaWord": "ವಾ"
  },
  {
    "id": 96,
    "year": 1700,
    "encoding": "BN167",
    "place": "Kalkere",
    "lineNumber": 8,
    "posNumber": 1,
    "letter": "vŏ",
    "fileName": "1700_BN167_Kalkere_8_1_vŏ",
    "filePath": "vŏ/vŏ_form1/1700_BN167_Kalkere_8_1_vŏ.png",
    "kannadaWord": "ವೊ"
  },
  {
    "id": 97,
    "year": 1700,
    "encoding": "BN167",
    "place": "Kalkere",
    "lineNumber": 6,
    "posNumber": 9,
    "letter": "vŏ",
    "fileName": "1700_BN167_Kalkere_6_9_vŏ",
    "filePath": "vŏ/vŏ_form2/1700_BN167_Kalkere_6_9_vŏ.png",
    "kannadaWord": "ವೊ"
  },
  {
    "id": 98,
    "year": 1700,
    "encoding": "BN167",
    "place": "Kalkere",
    "lineNumber": 11,
    "posNumber": 12,
    "letter": "ya",
    "fileName": "1700_BN167_Kalkere_11_12_ya",
    "filePath": "ya/ya_form1/1700_BN167_Kalkere_11_12_ya.png",
    "kannadaWord": "ಯ"
  },
  {
    "id": 99,
    "year": 1700,
    "encoding": "BN167",
    "place": "Kalkere",
    "lineNumber": 11,
    "posNumber": 9,
    "letter": "ya",
    "fileName": "1700_BN167_Kalkere_11_9_ya",
    "filePath": "ya/ya_form1/1700_BN167_Kalkere_11_9_ya.png",
    "kannadaWord": "ಯ"
  },
  {
    "id": 100,
    "year": 1700,
    "encoding": "BN167",
    "place": "Kalkere",
    "lineNumber": 2,
    "posNumber": 10,
    "letter": "ya",
    "fileName": "1700_BN167_Kalkere_2_10_ya",
    "filePath": "ya/ya_form1/1700_BN167_Kalkere_2_10_ya.png",
    "kannadaWord": "ಯ"
  },
  {
    "id": 101,
    "year": 1700,
    "encoding": "BN167",
    "place": "Kalkere",
    "lineNumber": 3,
    "posNumber": 1,
    "letter": "ya",
    "fileName": "1700_BN167_Kalkere_3_1_ya",
    "filePath": "ya/ya_form1/1700_BN167_Kalkere_3_1_ya.png",
    "kannadaWord": "ಯ"
  },
  {
    "id": 102,
    "year": 1700,
    "encoding": "BN167",
    "place": "Kalkere",
    "lineNumber": 3,
    "posNumber": 8,
    "letter": "ya",
    "fileName": "1700_BN167_Kalkere_3_8_ya",
    "filePath": "ya/ya_form1/1700_BN167_Kalkere_3_8_ya.png",
    "kannadaWord": "ಯ"
  },
  {
    "id": 103,
    "year": 1700,
    "encoding": "BN167",
    "place": "Kalkere",
    "lineNumber": 4,
    "posNumber": 5,
    "letter": "ya",
    "fileName": "1700_BN167_Kalkere_4_5_ya",
    "filePath": "ya/ya_form1/1700_BN167_Kalkere_4_5_ya.png",
    "kannadaWord": "ಯ"
  },
  {
    "id": 104,
    "year": 1700,
    "encoding": "BN167",
    "place": "Kalkere",
    "lineNumber": 4,
    "posNumber": 8,
    "letter": "ya",
    "fileName": "1700_BN167_Kalkere_4_8_ya",
    "filePath": "ya/ya_form1/1700_BN167_Kalkere_4_8_ya.png",
    "kannadaWord": "ಯ"
  },
  {
    "id": 105,
    "year": 1700,
    "encoding": "BN167",
    "place": "Kalkere",
    "lineNumber": 5,
    "posNumber": 11,
    "letter": "ya",
    "fileName": "1700_BN167_Kalkere_5_11_ya",
    "filePath": "ya/ya_form1/1700_BN167_Kalkere_5_11_ya.png",
    "kannadaWord": "ಯ"
  },
  {
    "id": 106,
    "year": 1700,
    "encoding": "BN167",
    "place": "Kalkere",
    "lineNumber": 5,
    "posNumber": 1,
    "letter": "ya",
    "fileName": "1700_BN167_Kalkere_5_1_ya",
    "filePath": "ya/ya_form1/1700_BN167_Kalkere_5_1_ya.png",
    "kannadaWord": "ಯ"
  },
  {
    "id": 107,
    "year": 1700,
    "encoding": "BN167",
    "place": "Kalkere",
    "lineNumber": 6,
    "posNumber": 11,
    "letter": "ya",
    "fileName": "1700_BN167_Kalkere_6_11_ya",
    "filePath": "ya/ya_form1/1700_BN167_Kalkere_6_11_ya.png",
    "kannadaWord": "ಯ"
  },
  {
    "id": 108,
    "year": 1700,
    "encoding": "BN167",
    "place": "Kalkere",
    "lineNumber": 6,
    "posNumber": 2,
    "letter": "ya",
    "fileName": "1700_BN167_Kalkere_6_2_ya",
    "filePath": "ya/ya_form1/1700_BN167_Kalkere_6_2_ya.png",
    "kannadaWord": "ಯ"
  },
  {
    "id": 109,
    "year": 1700,
    "encoding": "BN167",
    "place": "Kalkere",
    "lineNumber": 6,
    "posNumber": 4,
    "letter": "ya",
    "fileName": "1700_BN167_Kalkere_6_4_ya",
    "filePath": "ya/ya_form1/1700_BN167_Kalkere_6_4_ya.png",
    "kannadaWord": "ಯ"
  },
  {
    "id": 110,
    "year": 1700,
    "encoding": "BN167",
    "place": "Kalkere",
    "lineNumber": 7,
    "posNumber": 2,
    "letter": "ya",
    "fileName": "1700_BN167_Kalkere_7_2_ya",
    "filePath": "ya/ya_form1/1700_BN167_Kalkere_7_2_ya.png",
    "kannadaWord": "ಯ"
  },
  {
    "id": 111,
    "year": 1700,
    "encoding": "BN167",
    "place": "Kalkere",
    "lineNumber": 7,
    "posNumber": 5,
    "letter": "ya",
    "fileName": "1700_BN167_Kalkere_7_5_ya",
    "filePath": "ya/ya_form1/1700_BN167_Kalkere_7_5_ya.png",
    "kannadaWord": "ಯ"
  },
  {
    "id": 112,
    "year": 1700,
    "encoding": "BN167",
    "place": "Kalkere",
    "lineNumber": 8,
    "posNumber": 3,
    "letter": "ya",
    "fileName": "1700_BN167_Kalkere_8_3_ya",
    "filePath": "ya/ya_form1/1700_BN167_Kalkere_8_3_ya.png",
    "kannadaWord": "ಯ"
  },
  {
    "id": 113,
    "year": 1700,
    "encoding": "BN167",
    "place": "Kalkere",
    "lineNumber": 9,
    "posNumber": 14,
    "letter": "ya",
    "fileName": "1700_BN167_Kalkere_9_14_ya",
    "filePath": "ya/ya_form1/1700_BN167_Kalkere_9_14_ya.png",
    "kannadaWord": "ಯ"
  },
  {
    "id": 114,
    "year": 1700,
    "encoding": "BN167",
    "place": "Kalkere",
    "lineNumber": 10,
    "posNumber": 7,
    "letter": "yi",
    "fileName": "1700_BN167_Kalkere_10_7_yi",
    "filePath": "yi/yi_form1/1700_BN167_Kalkere_10_7_yi.png",
    "kannadaWord": "ಯಿ"
  },
  {
    "id": 115,
    "year": 1700,
    "encoding": "BN167",
    "place": "Kalkere",
    "lineNumber": 1,
    "posNumber": 10,
    "letter": "yi",
    "fileName": "1700_BN167_Kalkere_1_10_yi",
    "filePath": "yi/yi_form1/1700_BN167_Kalkere_1_10_yi.png",
    "kannadaWord": "ಯಿ"
  },
  {
    "id": 116,
    "year": 1700,
    "encoding": "BN167",
    "place": "Kalkere",
    "lineNumber": 2,
    "posNumber": 7,
    "letter": "yi",
    "fileName": "1700_BN167_Kalkere_2_7_yi",
    "filePath": "yi/yi_form1/1700_BN167_Kalkere_2_7_yi.png",
    "kannadaWord": "ಯಿ"
  },
  {
    "id": 117,
    "year": 1700,
    "encoding": "BN167",
    "place": "Kalkere",
    "lineNumber": 7,
    "posNumber": 7,
    "letter": "yī",
    "fileName": "1700_BN167_Kalkere_7_7_yī",
    "filePath": "yī/yī_form1/1700_BN167_Kalkere_7_7_yī.png",
    "kannadaWord": "ಯೀ"
  },
  {
    "id": 118,
    "year": 1700,
    "encoding": "BN167",
    "place": "Kalkere",
    "lineNumber": 10,
    "posNumber": 10,
    "letter": "ā",
    "fileName": "1700_BN167_Kalkere_10_10_ā",
    "filePath": "ā/ā_form1/1700_BN167_Kalkere_10_10_ā.png",
    "kannadaWord": "ಆ"
  },
  {
    "id": 119,
    "year": 1700,
    "encoding": "BN167",
    "place": "Kalkere",
    "lineNumber": 2,
    "posNumber": 8,
    "letter": "ĕ",
    "fileName": "1700_BN167_Kalkere_2_8_ĕ",
    "filePath": "ĕ/ĕ_form1/1700_BN167_Kalkere_2_8_ĕ.png",
    "kannadaWord": "ಎ"
  },
  {
    "id": 120,
    "year": 1700,
    "encoding": "BN167",
    "place": "Kalkere",
    "lineNumber": 3,
    "posNumber": 11,
    "letter": "ŏ",
    "fileName": "1700_BN167_Kalkere_3_11_ŏ",
    "filePath": "ŏ/ŏ_form1/1700_BN167_Kalkere_3_11_ŏ.png",
    "kannadaWord": "ಒ"
  },
  {
    "id": 121,
    "year": 1700,
    "encoding": "BN167",
    "place": "Kalkere",
    "lineNumber": 6,
    "posNumber": 3,
    "letter": "ŏ",
    "fileName": "1700_BN167_Kalkere_6_3_ŏ",
    "filePath": "ŏ/ŏ_form1/1700_BN167_Kalkere_6_3_ŏ.png",
    "kannadaWord": "ಒ"
  },
  {
    "id": 122,
    "year": 1700,
    "encoding": "BN167",
    "place": "Kalkere",
    "lineNumber": 7,
    "posNumber": 3,
    "letter": "ŏ",
    "fileName": "1700_BN167_Kalkere_7_3_ŏ",
    "filePath": "ŏ/ŏ_form1/1700_BN167_Kalkere_7_3_ŏ.png",
    "kannadaWord": "ಒ"
  },
  {
    "id": 123,
    "year": 1700,
    "encoding": "BN167",
    "place": "Kalkere",
    "lineNumber": 9,
    "posNumber": 12,
    "letter": "ŏ",
    "fileName": "1700_BN167_Kalkere_9_12_ŏ",
    "filePath": "ŏ/ŏ_form1/1700_BN167_Kalkere_9_12_ŏ.png",
    "kannadaWord": "ಒ"
  },
  {
    "id": 124,
    "year": 1700,
    "encoding": "BN167",
    "place": "Kalkere",
    "lineNumber": 11,
    "posNumber": 11,
    "letter": "ḍi",
    "fileName": "1700_BN167_Kalkere_11_11_ḍi",
    "filePath": "ḍi/ḍi_form1/1700_BN167_Kalkere_11_11_ḍi.png",
    "kannadaWord": "ಡಿ"
  },
  {
    "id": 125,
    "year": 1700,
    "encoding": "BN167",
    "place": "Kalkere",
    "lineNumber": 6,
    "posNumber": 10,
    "letter": "ḍĕ",
    "fileName": "1700_BN167_Kalkere_6_10_ḍĕ",
    "filePath": "ḍĕ/ḍĕ_form1/1700_BN167_Kalkere_6_10_ḍĕ.png",
    "kannadaWord": "ಡೆ"
  },
  {
    "id": 126,
    "year": 1700,
    "encoding": "BN167",
    "place": "Kalkere",
    "lineNumber": 6,
    "posNumber": 5,
    "letter": "ḍĕ",
    "fileName": "1700_BN167_Kalkere_6_5_ḍĕ",
    "filePath": "ḍĕ/ḍĕ_form1/1700_BN167_Kalkere_6_5_ḍĕ.png",
    "kannadaWord": "ಡೆ"
  },
  {
    "id": 127,
    "year": 1700,
    "encoding": "BN167",
    "place": "Kalkere",
    "lineNumber": 7,
    "posNumber": 4,
    "letter": "ḍĕ",
    "fileName": "1700_BN167_Kalkere_7_4_ḍĕ",
    "filePath": "ḍĕ/ḍĕ_form1/1700_BN167_Kalkere_7_4_ḍĕ.png",
    "kannadaWord": "ಡೆ"
  },
  {
    "id": 128,
    "year": 1700,
    "encoding": "BN167",
    "place": "Kalkere",
    "lineNumber": 8,
    "posNumber": 2,
    "letter": "ḍĕ",
    "fileName": "1700_BN167_Kalkere_8_2_ḍĕ",
    "filePath": "ḍĕ/ḍĕ_form1/1700_BN167_Kalkere_8_2_ḍĕ.png",
    "kannadaWord": "ಡೆ"
  },
  {
    "id": 129,
    "year": 1700,
    "encoding": "BN167",
    "place": "Kalkere",
    "lineNumber": 9,
    "posNumber": 13,
    "letter": "ḍĕ",
    "fileName": "1700_BN167_Kalkere_9_13_ḍĕ",
    "filePath": "ḍĕ/ḍĕ_form1/1700_BN167_Kalkere_9_13_ḍĕ.png",
    "kannadaWord": "ಡೆ"
  },
  {
    "id": 130,
    "year": 1700,
    "encoding": "BN167",
    "place": "Kalkere",
    "lineNumber": 4,
    "posNumber": 11,
    "letter": "ṇa",
    "fileName": "1700_BN167_Kalkere_4_11_ṇa",
    "filePath": "ṇa/ṇa_form2/1700_BN167_Kalkere_4_11_ṇa.png",
    "kannadaWord": "ಣ"
  },
  {
    "id": 131,
    "year": 1700,
    "encoding": "BN167",
    "place": "Kalkere",
    "lineNumber": 3,
    "posNumber": 7,
    "letter": "ṟĕ",
    "fileName": "1700_BN167_Kalkere_3_7_ṟĕ",
    "filePath": "ṟĕ/ṟĕ_form1/1700_BN167_Kalkere_3_7_ṟĕ.png",
    "kannadaWord": "ಱೆ"
  },
  {
    "id": 132,
    "year": 1700,
    "encoding": "BN167",
    "place": "Kalkere",
    "lineNumber": 4,
    "posNumber": 7,
    "letter": "ṟĕ",
    "fileName": "1700_BN167_Kalkere_4_7_ṟĕ",
    "filePath": "ṟĕ/ṟĕ_form1/1700_BN167_Kalkere_4_7_ṟĕ.png",
    "kannadaWord": "ಱೆ"
  },
  {
    "id": 133,
    "year": 1700,
    "encoding": "BN167",
    "place": "Kalkere",
    "lineNumber": 5,
    "posNumber": 10,
    "letter": "ṟĕ",
    "fileName": "1700_BN167_Kalkere_5_10_ṟĕ",
    "filePath": "ṟĕ/ṟĕ_form1/1700_BN167_Kalkere_5_10_ṟĕ.png",
    "kannadaWord": "ಱೆ"
  },
  {
    "id": 134,
    "year": 1700,
    "encoding": "BN167",
    "place": "Kalkere",
    "lineNumber": 10,
    "posNumber": 4,
    "letter": "ṭṭa",
    "fileName": "1700_BN167_Kalkere_10_4_ṭṭa",
    "filePath": "ṭṭa/ṭṭa_form2/1700_BN167_Kalkere_10_4_ṭṭa.png",
    "kannadaWord": "ಟ್ಟ"
  },
  {
    "id": 135,
    "year": 1700,
    "encoding": "BN167",
    "place": "Kalkere",
    "lineNumber": 4,
    "posNumber": 4,
    "letter": "ṭṭi",
    "fileName": "1700_BN167_Kalkere_4_4_ṭṭi",
    "filePath": "ṭṭi/ṭṭi_form2/1700_BN167_Kalkere_4_4_ṭṭi.png",
    "kannadaWord": "ಟ್ಟಿ"
  },
  {
    "id": 136,
    "year": 1700,
    "encoding": "BN167",
    "place": "Kalkere",
    "lineNumber": 5,
    "posNumber": 6,
    "letter": "ṭṭi",
    "fileName": "1700_BN167_Kalkere_5_6_ṭṭi",
    "filePath": "ṭṭi/ṭṭi_form2/1700_BN167_Kalkere_5_6_ṭṭi.png",
    "kannadaWord": "ಟ್ಟಿ"
  }
]