[
  {
    "id": 1,
    "year": 750,
    "encoding": "BN55",
    "place": "KRPuram",
    "lineNumber": 3,
    "posNumber": 9,
    "letter": "bi",
    "fileName": "750_BN55_KRPuram_3_9_bi",
    "filePath": "bi/bi_form1/750_BN55_KRPuram_3_9_bi.png",
    "kannadaWord": "ಬಿ"
  },
  {
    "id": 2,
    "year": 750,
    "encoding": "BN55",
    "place": "KRPuram",
    "lineNumber": 3,
    "posNumber": 8,
    "letter": "du",
    "fileName": "750_BN55_KRPuram_3_8_du",
    "filePath": "du/du_form1/750_BN55_KRPuram_3_8_du.png",
    "kannadaWord": "ದು"
  },
  {
    "id": 3,
    "year": 750,
    "encoding": "BN55",
    "place": "KRPuram",
    "lineNumber": 3,
    "posNumber": 6,
    "letter": "dĕ",
    "fileName": "750_BN55_KRPuram_3_6_dĕ",
    "filePath": "dĕ/dĕ_form1/750_BN55_KRPuram_3_6_dĕ.png",
    "kannadaWord": "ದೆ"
  },
  {
    "id": 4,
    "year": 750,
    "encoding": "BN55",
    "place": "KRPuram",
    "lineNumber": 1,
    "posNumber": 12,
    "letter": "gĕ",
    "fileName": "750_BN55_KRPuram_1_12_gĕ",
    "filePath": "gĕ/gĕ_form1/750_BN55_KRPuram_1_12_gĕ.png",
    "kannadaWord": "ಗೆ"
  },
  {
    "id": 5,
    "year": 750,
    "encoding": "BN55",
    "place": "KRPuram",
    "lineNumber": 1,
    "posNumber": 6,
    "letter": "hā",
    "fileName": "750_BN55_KRPuram_1_6_hā",
    "filePath": "hā/hā_form1/750_BN55_KRPuram_1_6_hā.png",
    "kannadaWord": "ಹಾ"
  },
  {
    "id": 6,
    "year": 750,
    "encoding": "BN55",
    "place": "KRPuram",
    "lineNumber": 1,
    "posNumber": 8,
    "letter": "ja",
    "fileName": "750_BN55_KRPuram_1_8_ja",
    "filePath": "ja/ja_form1/750_BN55_KRPuram_1_8_ja.png",
    "kannadaWord": "ಜ"
  },
  {
    "id": 7,
    "year": 750,
    "encoding": "BN55",
    "place": "KRPuram",
    "lineNumber": 1,
    "posNumber": 14,
    "letter": "ka",
    "fileName": "750_BN55_KRPuram_1_14_ka",
    "filePath": "ka/ka_form1/750_BN55_KRPuram_1_14_ka.png",
    "kannadaWord": "ಕ"
  },
  {
    "id": 8,
    "year": 750,
    "encoding": "BN55",
    "place": "KRPuram",
    "lineNumber": 2,
    "posNumber": 3,
    "letter": "ka",
    "fileName": "750_BN55_KRPuram_2_3_ka",
    "filePath": "ka/ka_form1/750_BN55_KRPuram_2_3_ka.png",
    "kannadaWord": "ಕ"
  },
  {
    "id": 9,
    "year": 750,
    "encoding": "BN55",
    "place": "KRPuram",
    "lineNumber": 2,
    "posNumber": 12,
    "letter": "lgŏ",
    "fileName": "750_BN55_KRPuram_2_12_lgŏ",
    "filePath": "lgŏ/lgŏ_form1/750_BN55_KRPuram_2_12_lgŏ.png",
    "kannadaWord": "ಲ್ಗೊ"
  },
  {
    "id": 10,
    "year": 750,
    "encoding": "BN55",
    "place": "KRPuram",
    "lineNumber": 2,
    "posNumber": 6,
    "letter": "l̤i",
    "fileName": "750_BN55_KRPuram_2_6_l̤i",
    "filePath": "l̤i/l̤i_form1/750_BN55_KRPuram_2_6_l̤i.png",
    "kannadaWord": "ಳಿ"
  },
  {
    "id": 11,
    "year": 750,
    "encoding": "BN55",
    "place": "KRPuram",
    "lineNumber": 1,
    "posNumber": 5,
    "letter": "ma",
    "fileName": "750_BN55_KRPuram_1_5_ma",
    "filePath": "ma/ma_form1/750_BN55_KRPuram_1_5_ma.png",
    "kannadaWord": "ಮ"
  },
  {
    "id": 12,
    "year": 750,
    "encoding": "BN55",
    "place": "KRPuram",
    "lineNumber": 1,
    "posNumber": 15,
    "letter": "nna",
    "fileName": "750_BN55_KRPuram_1_15_nna",
    "filePath": "nna/nna_form1/750_BN55_KRPuram_1_15_nna.png",
    "kannadaWord": "ನ್ನ"
  },
  {
    "id": 13,
    "year": 750,
    "encoding": "BN55",
    "place": "KRPuram",
    "lineNumber": 2,
    "posNumber": 14,
    "letter": "nu",
    "fileName": "750_BN55_KRPuram_2_14_nu",
    "filePath": "nu/nu_form1/750_BN55_KRPuram_2_14_nu.png",
    "kannadaWord": "ನು"
  },
  {
    "id": 14,
    "year": 750,
    "encoding": "BN55",
    "place": "KRPuram",
    "lineNumber": 3,
    "posNumber": 5,
    "letter": "nu",
    "fileName": "750_BN55_KRPuram_3_5_nu",
    "filePath": "nu/nu_form1/750_BN55_KRPuram_3_5_nu.png",
    "kannadaWord": "ನು"
  },
  {
    "id": 15,
    "year": 750,
    "encoding": "BN55",
    "place": "KRPuram",
    "lineNumber": 1,
    "posNumber": 2,
    "letter": "pu",
    "fileName": "750_BN55_KRPuram_1_2_pu",
    "filePath": "pu/pu_form1/750_BN55_KRPuram_1_2_pu.png",
    "kannadaWord": "ಪು"
  },
  {
    "id": 16,
    "year": 750,
    "encoding": "BN55",
    "place": "KRPuram",
    "lineNumber": 2,
    "posNumber": 1,
    "letter": "pŏ",
    "fileName": "750_BN55_KRPuram_2_1_pŏ",
    "filePath": "pŏ/pŏ_form1/750_BN55_KRPuram_2_1_pŏ.png",
    "kannadaWord": "ಪೊ"
  },
  {
    "id": 17,
    "year": 750,
    "encoding": "BN55",
    "place": "KRPuram",
    "lineNumber": 2,
    "posNumber": 7,
    "letter": "pŏ",
    "fileName": "750_BN55_KRPuram_2_7_pŏ",
    "filePath": "pŏ/pŏ_form1/750_BN55_KRPuram_2_7_pŏ.png",
    "kannadaWord": "ಪೊ"
  },
  {
    "id": 18,
    "year": 750,
    "encoding": "BN55",
    "place": "KRPuram",
    "lineNumber": 1,
    "posNumber": 10,
    "letter": "ra",
    "fileName": "750_BN55_KRPuram_1_10_ra",
    "filePath": "ra/ra_form1/750_BN55_KRPuram_1_10_ra.png",
    "kannadaWord": "ರ"
  },
  {
    "id": 19,
    "year": 750,
    "encoding": "BN55",
    "place": "KRPuram",
    "lineNumber": 1,
    "posNumber": 16,
    "letter": "ra",
    "fileName": "750_BN55_KRPuram_1_16_ra",
    "filePath": "ra/ra_form1/750_BN55_KRPuram_1_16_ra.png",
    "kannadaWord": "ರ"
  },
  {
    "id": 20,
    "year": 750,
    "encoding": "BN55",
    "place": "KRPuram",
    "lineNumber": 1,
    "posNumber": 9,
    "letter": "ra",
    "fileName": "750_BN55_KRPuram_1_9_ra",
    "filePath": "ra/ra_form1/750_BN55_KRPuram_1_9_ra.png",
    "kannadaWord": "ರ"
  },
  {
    "id": 21,
    "year": 750,
    "encoding": "BN55",
    "place": "KRPuram",
    "lineNumber": 2,
    "posNumber": 10,
    "letter": "ra",
    "fileName": "750_BN55_KRPuram_2_10_ra",
    "filePath": "ra/ra_form1/750_BN55_KRPuram_2_10_ra.png",
    "kannadaWord": "ರ"
  },
  {
    "id": 22,
    "year": 750,
    "encoding": "BN55",
    "place": "KRPuram",
    "lineNumber": 2,
    "posNumber": 11,
    "letter": "ra",
    "fileName": "750_BN55_KRPuram_2_11_ra",
    "filePath": "ra/ra_form1/750_BN55_KRPuram_2_11_ra.png",
    "kannadaWord": "ರ"
  },
  {
    "id": 23,
    "year": 750,
    "encoding": "BN55",
    "place": "KRPuram",
    "lineNumber": 3,
    "posNumber": 2,
    "letter": "ra",
    "fileName": "750_BN55_KRPuram_3_2_ra",
    "filePath": "ra/ra_form1/750_BN55_KRPuram_3_2_ra.png",
    "kannadaWord": "ರ"
  },
  {
    "id": 24,
    "year": 750,
    "encoding": "BN55",
    "place": "KRPuram",
    "lineNumber": 3,
    "posNumber": 11,
    "letter": "ra",
    "fileName": "750_BN55_KRPuram_3_11_ra",
    "filePath": "ra/ra_form2/750_BN55_KRPuram_3_11_ra.png",
    "kannadaWord": "ರ"
  },
  {
    "id": 25,
    "year": 750,
    "encoding": "BN55",
    "place": "KRPuram",
    "lineNumber": 2,
    "posNumber": 2,
    "letter": "rbāṃ",
    "fileName": "750_BN55_KRPuram_2_2_rbāṃ",
    "filePath": "rbāṃ/rbāṃ_form1/750_BN55_KRPuram_2_2_rbāṃ.png",
    "kannadaWord": "ರ್ಬಾಂ"
  },
  {
    "id": 26,
    "year": 750,
    "encoding": "BN55",
    "place": "KRPuram",
    "lineNumber": 1,
    "posNumber": 3,
    "letter": "ru",
    "fileName": "750_BN55_KRPuram_1_3_ru",
    "filePath": "ru/ru_form1/750_BN55_KRPuram_1_3_ru.png",
    "kannadaWord": "ರು"
  },
  {
    "id": 27,
    "year": 750,
    "encoding": "BN55",
    "place": "KRPuram",
    "lineNumber": 2,
    "posNumber": 4,
    "letter": "ru",
    "fileName": "750_BN55_KRPuram_2_4_ru",
    "filePath": "ru/ru_form1/750_BN55_KRPuram_2_4_ru.png",
    "kannadaWord": "ರು"
  },
  {
    "id": 28,
    "year": 750,
    "encoding": "BN55",
    "place": "KRPuram",
    "lineNumber": 1,
    "posNumber": 7,
    "letter": "rā",
    "fileName": "750_BN55_KRPuram_1_7_rā",
    "filePath": "rā/rā_form1/750_BN55_KRPuram_1_7_rā.png",
    "kannadaWord": "ರಾ"
  },
  {
    "id": 29,
    "year": 750,
    "encoding": "BN55",
    "place": "KRPuram",
    "lineNumber": 2,
    "posNumber": 5,
    "letter": "rā",
    "fileName": "750_BN55_KRPuram_2_5_rā",
    "filePath": "rā/rā_form1/750_BN55_KRPuram_2_5_rā.png",
    "kannadaWord": "ರಾ"
  },
  {
    "id": 30,
    "year": 750,
    "encoding": "BN55",
    "place": "KRPuram",
    "lineNumber": 2,
    "posNumber": 8,
    "letter": "sa",
    "fileName": "750_BN55_KRPuram_2_8_sa",
    "filePath": "sa/sa_form1/750_BN55_KRPuram_2_8_sa.png",
    "kannadaWord": "ಸ"
  },
  {
    "id": 31,
    "year": 750,
    "encoding": "BN55",
    "place": "KRPuram",
    "lineNumber": 1,
    "posNumber": 11,
    "letter": "su",
    "fileName": "750_BN55_KRPuram_1_11_su",
    "filePath": "su/su_form1/750_BN55_KRPuram_1_11_su.png",
    "kannadaWord": "ಸು"
  },
  {
    "id": 32,
    "year": 750,
    "encoding": "BN55",
    "place": "KRPuram",
    "lineNumber": 3,
    "posNumber": 1,
    "letter": "u",
    "fileName": "750_BN55_KRPuram_3_1_u",
    "filePath": "u/u_form1/750_BN55_KRPuram_3_1_u.png",
    "kannadaWord": "ಉ"
  },
  {
    "id": 33,
    "year": 750,
    "encoding": "BN55",
    "place": "KRPuram",
    "lineNumber": 3,
    "posNumber": 4,
    "letter": "vi",
    "fileName": "750_BN55_KRPuram_3_4_vi",
    "filePath": "vi/vi_form1/750_BN55_KRPuram_3_4_vi.png",
    "kannadaWord": "ವಿ"
  },
  {
    "id": 34,
    "year": 750,
    "encoding": "BN55",
    "place": "KRPuram",
    "lineNumber": 2,
    "posNumber": 13,
    "letter": "ya",
    "fileName": "750_BN55_KRPuram_2_13_ya",
    "filePath": "ya/ya_form2/750_BN55_KRPuram_2_13_ya.png",
    "kannadaWord": "ಯ"
  },
  {
    "id": 35,
    "year": 750,
    "encoding": "BN55",
    "place": "KRPuram",
    "lineNumber": 1,
    "posNumber": 13,
    "letter": "yĕ",
    "fileName": "750_BN55_KRPuram_1_13_yĕ",
    "filePath": "yĕ/yĕ_form1/750_BN55_KRPuram_1_13_yĕ.png",
    "kannadaWord": "ಯೆ"
  },
  {
    "id": 36,
    "year": 750,
    "encoding": "BN55",
    "place": "KRPuram",
    "lineNumber": 1,
    "posNumber": 1,
    "letter": "śrī",
    "fileName": "750_BN55_KRPuram_1_1_śrī",
    "filePath": "śrī/śrī_form1/750_BN55_KRPuram_1_1_śrī.png",
    "kannadaWord": "ಶ್ರೀ"
  },
  {
    "id": 37,
    "year": 750,
    "encoding": "BN55",
    "place": "KRPuram",
    "lineNumber": 2,
    "posNumber": 9,
    "letter": "ū",
    "fileName": "750_BN55_KRPuram_2_9_ū",
    "filePath": "ū/ū_form1/750_BN55_KRPuram_2_9_ū.png",
    "kannadaWord": "ಊ"
  },
  {
    "id": 38,
    "year": 750,
    "encoding": "BN55",
    "place": "KRPuram",
    "lineNumber": 3,
    "posNumber": 10,
    "letter": "ḻda",
    "fileName": "750_BN55_KRPuram_3_10_ḻda",
    "filePath": "ḻda/ḻda_form1/750_BN55_KRPuram_3_10_ḻda.png",
    "kannadaWord": "ೞ್ದ"
  },
  {
    "id": 39,
    "year": 750,
    "encoding": "BN55",
    "place": "KRPuram",
    "lineNumber": 3,
    "posNumber": 3,
    "letter": "ḻi",
    "fileName": "750_BN55_KRPuram_3_3_ḻi",
    "filePath": "ḻi/ḻi_form1/750_BN55_KRPuram_3_3_ḻi.png",
    "kannadaWord": "ೞಿ"
  },
  {
    "id": 40,
    "year": 750,
    "encoding": "BN55",
    "place": "KRPuram",
    "lineNumber": 3,
    "posNumber": 7,
    "letter": "ṟi",
    "fileName": "750_BN55_KRPuram_3_7_ṟi",
    "filePath": "ṟi/ṟi_form1/750_BN55_KRPuram_3_7_ṟi.png",
    "kannadaWord": "ಱಿ"
  },
  {
    "id": 41,
    "year": 750,
    "encoding": "BN55",
    "place": "KRPuram",
    "lineNumber": 1,
    "posNumber": 4,
    "letter": "ṣa",
    "fileName": "750_BN55_KRPuram_1_4_ṣa",
    "filePath": "ṣa/ṣa_form1/750_BN55_KRPuram_1_4_ṣa.png",
    "kannadaWord": "ಷ"
  }
]