[
  {
    "id": 1,
    "year": 971,
    "encoding": "Aksharameru",
    "place": "Nagavara",
    "lineNumber": 8,
    "posNumber": 4,
    "letter": "3",
    "fileName": "971_Aksharameru_Nagavara_8_4_3",
    "filePath": "3/3_form1/971_Aksharameru_Nagavara_8_4_3.JPG",
    "kannadaWord": "3"
  },
  {
    "id": 2,
    "year": 971,
    "encoding": "Aksharameru",
    "place": "Nagavara",
    "lineNumber": 8,
    "posNumber": 3,
    "letter": "9",
    "fileName": "971_Aksharameru_Nagavara_8_3_9",
    "filePath": "9/9_form1/971_Aksharameru_Nagavara_8_3_9.JPG",
    "kannadaWord": "9"
  },
  {
    "id": 3,
    "year": 971,
    "encoding": "Aksharameru",
    "place": "Nagavara",
    "lineNumber": 3,
    "posNumber": 8,
    "letter": "ba",
    "fileName": "971_Aksharameru_Nagavara_3_8_ba",
    "filePath": "ba/ba_form1/971_Aksharameru_Nagavara_3_8_ba.JPG",
    "kannadaWord": "ಬ"
  },
  {
    "id": 4,
    "year": 971,
    "encoding": "Aksharameru",
    "place": "Nagavara",
    "lineNumber": 4,
    "posNumber": 5,
    "letter": "ba",
    "fileName": "971_Aksharameru_Nagavara_4_5_ba",
    "filePath": "ba/ba_form1/971_Aksharameru_Nagavara_4_5_ba.JPG",
    "kannadaWord": "ಬ"
  },
  {
    "id": 5,
    "year": 971,
    "encoding": "Aksharameru",
    "place": "Nagavara",
    "lineNumber": 3,
    "posNumber": 5,
    "letter": "bha",
    "fileName": "971_Aksharameru_Nagavara_3_5_bha",
    "filePath": "bha/bha_form1/971_Aksharameru_Nagavara_3_5_bha.JPG",
    "kannadaWord": "ಭ"
  },
  {
    "id": 6,
    "year": 971,
    "encoding": "Aksharameru",
    "place": "Nagavara",
    "lineNumber": 6,
    "posNumber": 2,
    "letter": "bha",
    "fileName": "971_Aksharameru_Nagavara_6_2_bha",
    "filePath": "bha/bha_form1/971_Aksharameru_Nagavara_6_2_bha.JPG",
    "kannadaWord": "ಭ"
  },
  {
    "id": 7,
    "year": 971,
    "encoding": "Aksharameru",
    "place": "Nagavara",
    "lineNumber": 1,
    "posNumber": 8,
    "letter": "bhi",
    "fileName": "971_Aksharameru_Nagavara_1_8_bhi",
    "filePath": "bhi/bhi_form1/971_Aksharameru_Nagavara_1_8_bhi.JPG",
    "kannadaWord": "ಭಿ"
  },
  {
    "id": 8,
    "year": 971,
    "encoding": "Aksharameru",
    "place": "Nagavara",
    "lineNumber": 15,
    "posNumber": 2,
    "letter": "bhu",
    "fileName": "971_Aksharameru_Nagavara_15_2_bhu",
    "filePath": "bhu/bhu_form1/971_Aksharameru_Nagavara_15_2_bhu.JPG",
    "kannadaWord": "ಭು"
  },
  {
    "id": 9,
    "year": 971,
    "encoding": "Aksharameru",
    "place": "Nagavara",
    "lineNumber": 2,
    "posNumber": 8,
    "letter": "bhu",
    "fileName": "971_Aksharameru_Nagavara_2_8_bhu",
    "filePath": "bhu/bhu_form1/971_Aksharameru_Nagavara_2_8_bhu.JPG",
    "kannadaWord": "ಭು"
  },
  {
    "id": 10,
    "year": 971,
    "encoding": "Aksharameru",
    "place": "Nagavara",
    "lineNumber": 4,
    "posNumber": 7,
    "letter": "bhu",
    "fileName": "971_Aksharameru_Nagavara_4_7_bhu",
    "filePath": "bhu/bhu_form1/971_Aksharameru_Nagavara_4_7_bhu.JPG",
    "kannadaWord": "ಭು"
  },
  {
    "id": 11,
    "year": 971,
    "encoding": "Aksharameru",
    "place": "Nagavara",
    "lineNumber": 1,
    "posNumber": 10,
    "letter": "ca",
    "fileName": "971_Aksharameru_Nagavara_1_10_ca",
    "filePath": "ca/ca_form2/971_Aksharameru_Nagavara_1_10_ca.JPG",
    "kannadaWord": "ಚ"
  },
  {
    "id": 12,
    "year": 971,
    "encoding": "Aksharameru",
    "place": "Nagavara",
    "lineNumber": 5,
    "posNumber": 3,
    "letter": "cĕ",
    "fileName": "971_Aksharameru_Nagavara_5_3_cĕ",
    "filePath": "cĕ/cĕ_form1/971_Aksharameru_Nagavara_5_3_cĕ.JPG",
    "kannadaWord": "ಚೆ"
  },
  {
    "id": 13,
    "year": 971,
    "encoding": "Aksharameru",
    "place": "Nagavara",
    "lineNumber": 2,
    "posNumber": 1,
    "letter": "da",
    "fileName": "971_Aksharameru_Nagavara_2_1_da",
    "filePath": "da/da_form1/971_Aksharameru_Nagavara_2_1_da.JPG",
    "kannadaWord": "ದ"
  },
  {
    "id": 14,
    "year": 971,
    "encoding": "Aksharameru",
    "place": "Nagavara",
    "lineNumber": 11,
    "posNumber": 4,
    "letter": "da",
    "fileName": "971_Aksharameru_Nagavara_11_4_da",
    "filePath": "da/da_form2/971_Aksharameru_Nagavara_11_4_da.JPG",
    "kannadaWord": "ದ"
  },
  {
    "id": 15,
    "year": 971,
    "encoding": "Aksharameru",
    "place": "Nagavara",
    "lineNumber": 17,
    "posNumber": 4,
    "letter": "da",
    "fileName": "971_Aksharameru_Nagavara_17_4_da",
    "filePath": "da/da_form2/971_Aksharameru_Nagavara_17_4_da.JPG",
    "kannadaWord": "ದ"
  },
  {
    "id": 16,
    "year": 971,
    "encoding": "Aksharameru",
    "place": "Nagavara",
    "lineNumber": 1,
    "posNumber": 4,
    "letter": "da",
    "fileName": "971_Aksharameru_Nagavara_1_4_da",
    "filePath": "da/da_form2/971_Aksharameru_Nagavara_1_4_da.JPG",
    "kannadaWord": "ದ"
  },
  {
    "id": 17,
    "year": 971,
    "encoding": "Aksharameru",
    "place": "Nagavara",
    "lineNumber": 5,
    "posNumber": 9,
    "letter": "da",
    "fileName": "971_Aksharameru_Nagavara_5_9_da",
    "filePath": "da/da_form2/971_Aksharameru_Nagavara_5_9_da.JPG",
    "kannadaWord": "ದ"
  },
  {
    "id": 18,
    "year": 971,
    "encoding": "Aksharameru",
    "place": "Nagavara",
    "lineNumber": 5,
    "posNumber": 1,
    "letter": "daṃ",
    "fileName": "971_Aksharameru_Nagavara_5_1_daṃ",
    "filePath": "daṃ/daṃ_form1/971_Aksharameru_Nagavara_5_1_daṃ.JPG",
    "kannadaWord": "ದಂ"
  },
  {
    "id": 19,
    "year": 971,
    "encoding": "Aksharameru",
    "place": "Nagavara",
    "lineNumber": 16,
    "posNumber": 5,
    "letter": "di",
    "fileName": "971_Aksharameru_Nagavara_16_5_di",
    "filePath": "di/di_form1/971_Aksharameru_Nagavara_16_5_di.JPG",
    "kannadaWord": "ದಿ"
  },
  {
    "id": 20,
    "year": 971,
    "encoding": "Aksharameru",
    "place": "Nagavara",
    "lineNumber": 14,
    "posNumber": 4,
    "letter": "dŏ",
    "fileName": "971_Aksharameru_Nagavara_14_4_dŏ",
    "filePath": "dŏ/dŏ_form1/971_Aksharameru_Nagavara_14_4_dŏ.JPG",
    "kannadaWord": "ದೊ"
  },
  {
    "id": 21,
    "year": 971,
    "encoding": "Aksharameru",
    "place": "Nagavara",
    "lineNumber": 9,
    "posNumber": 2,
    "letter": "dŏ",
    "fileName": "971_Aksharameru_Nagavara_9_2_dŏ",
    "filePath": "dŏ/dŏ_form1/971_Aksharameru_Nagavara_9_2_dŏ.JPG",
    "kannadaWord": "ದೊ"
  },
  {
    "id": 22,
    "year": 971,
    "encoding": "Aksharameru",
    "place": "Nagavara",
    "lineNumber": 14,
    "posNumber": 3,
    "letter": "ga",
    "fileName": "971_Aksharameru_Nagavara_14_3_ga",
    "filePath": "ga/ga_form1/971_Aksharameru_Nagavara_14_3_ga.JPG",
    "kannadaWord": "ಗ"
  },
  {
    "id": 23,
    "year": 971,
    "encoding": "Aksharameru",
    "place": "Nagavara",
    "lineNumber": 15,
    "posNumber": 3,
    "letter": "ga",
    "fileName": "971_Aksharameru_Nagavara_15_3_ga",
    "filePath": "ga/ga_form1/971_Aksharameru_Nagavara_15_3_ga.JPG",
    "kannadaWord": "ಗ"
  },
  {
    "id": 24,
    "year": 971,
    "encoding": "Aksharameru",
    "place": "Nagavara",
    "lineNumber": 5,
    "posNumber": 8,
    "letter": "ga",
    "fileName": "971_Aksharameru_Nagavara_5_8_ga",
    "filePath": "ga/ga_form1/971_Aksharameru_Nagavara_5_8_ga.JPG",
    "kannadaWord": "ಗ"
  },
  {
    "id": 25,
    "year": 971,
    "encoding": "Aksharameru",
    "place": "Nagavara",
    "lineNumber": 6,
    "posNumber": 5,
    "letter": "ga",
    "fileName": "971_Aksharameru_Nagavara_6_5_ga",
    "filePath": "ga/ga_form1/971_Aksharameru_Nagavara_6_5_ga.JPG",
    "kannadaWord": "ಗ"
  },
  {
    "id": 26,
    "year": 971,
    "encoding": "Aksharameru",
    "place": "Nagavara",
    "lineNumber": 7,
    "posNumber": 1,
    "letter": "ga",
    "fileName": "971_Aksharameru_Nagavara_7_1_ga",
    "filePath": "ga/ga_form1/971_Aksharameru_Nagavara_7_1_ga.JPG",
    "kannadaWord": "ಗ"
  },
  {
    "id": 27,
    "year": 971,
    "encoding": "Aksharameru",
    "place": "Nagavara",
    "lineNumber": 12,
    "posNumber": 4,
    "letter": "ga",
    "fileName": "971_Aksharameru_Nagavara_12_4_ga",
    "filePath": "ga/ga_form2/971_Aksharameru_Nagavara_12_4_ga.JPG",
    "kannadaWord": "ಗ"
  },
  {
    "id": 28,
    "year": 971,
    "encoding": "Aksharameru",
    "place": "Nagavara",
    "lineNumber": 17,
    "posNumber": 2,
    "letter": "ggi",
    "fileName": "971_Aksharameru_Nagavara_17_2_ggi",
    "filePath": "ggi/ggi_form1/971_Aksharameru_Nagavara_17_2_ggi.JPG",
    "kannadaWord": "ಗ್ಗಿ"
  },
  {
    "id": 29,
    "year": 971,
    "encoding": "Aksharameru",
    "place": "Nagavara",
    "lineNumber": 16,
    "posNumber": 2,
    "letter": "gu",
    "fileName": "971_Aksharameru_Nagavara_16_2_gu",
    "filePath": "gu/gu_form1/971_Aksharameru_Nagavara_16_2_gu.JPG",
    "kannadaWord": "ಗು"
  },
  {
    "id": 30,
    "year": 971,
    "encoding": "Aksharameru",
    "place": "Nagavara",
    "lineNumber": 10,
    "posNumber": 2,
    "letter": "gā",
    "fileName": "971_Aksharameru_Nagavara_10_2_gā",
    "filePath": "gā/gā_form1/971_Aksharameru_Nagavara_10_2_gā.JPG",
    "kannadaWord": "ಗಾ"
  },
  {
    "id": 31,
    "year": 971,
    "encoding": "Aksharameru",
    "place": "Nagavara",
    "lineNumber": 6,
    "posNumber": 4,
    "letter": "gĕ",
    "fileName": "971_Aksharameru_Nagavara_6_4_gĕ",
    "filePath": "gĕ/gĕ_form1/971_Aksharameru_Nagavara_6_4_gĕ.JPG",
    "kannadaWord": "ಗೆ"
  },
  {
    "id": 32,
    "year": 971,
    "encoding": "Aksharameru",
    "place": "Nagavara",
    "lineNumber": 7,
    "posNumber": 6,
    "letter": "gĕ",
    "fileName": "971_Aksharameru_Nagavara_7_6_gĕ",
    "filePath": "gĕ/gĕ_form1/971_Aksharameru_Nagavara_7_6_gĕ.JPG",
    "kannadaWord": "ಗೆ"
  },
  {
    "id": 33,
    "year": 971,
    "encoding": "Aksharameru",
    "place": "Nagavara",
    "lineNumber": 11,
    "posNumber": 2,
    "letter": "gŏ",
    "fileName": "971_Aksharameru_Nagavara_11_2_gŏ",
    "filePath": "gŏ/gŏ_form2/971_Aksharameru_Nagavara_11_2_gŏ.JPG",
    "kannadaWord": "ಗೊ"
  },
  {
    "id": 34,
    "year": 971,
    "encoding": "Aksharameru",
    "place": "Nagavara",
    "lineNumber": 3,
    "posNumber": 7,
    "letter": "ha",
    "fileName": "971_Aksharameru_Nagavara_3_7_ha",
    "filePath": "ha/ha_form1/971_Aksharameru_Nagavara_3_7_ha.JPG",
    "kannadaWord": "ಹ"
  },
  {
    "id": 35,
    "year": 971,
    "encoding": "Aksharameru",
    "place": "Nagavara",
    "lineNumber": 13,
    "posNumber": 1,
    "letter": "i",
    "fileName": "971_Aksharameru_Nagavara_13_1_i",
    "filePath": "i/i_form1/971_Aksharameru_Nagavara_13_1_i.JPG",
    "kannadaWord": "ಇ"
  },
  {
    "id": 36,
    "year": 971,
    "encoding": "Aksharameru",
    "place": "Nagavara",
    "lineNumber": 2,
    "posNumber": 11,
    "letter": "ja",
    "fileName": "971_Aksharameru_Nagavara_2_11_ja",
    "filePath": "ja/ja_form1/971_Aksharameru_Nagavara_2_11_ja.JPG",
    "kannadaWord": "ಜ"
  },
  {
    "id": 37,
    "year": 971,
    "encoding": "Aksharameru",
    "place": "Nagavara",
    "lineNumber": 2,
    "posNumber": 9,
    "letter": "ja",
    "fileName": "971_Aksharameru_Nagavara_2_9_ja",
    "filePath": "ja/ja_form1/971_Aksharameru_Nagavara_2_9_ja.JPG",
    "kannadaWord": "ಜ"
  },
  {
    "id": 38,
    "year": 971,
    "encoding": "Aksharameru",
    "place": "Nagavara",
    "lineNumber": 8,
    "posNumber": 6,
    "letter": "ja",
    "fileName": "971_Aksharameru_Nagavara_8_6_ja",
    "filePath": "ja/ja_form1/971_Aksharameru_Nagavara_8_6_ja.JPG",
    "kannadaWord": "ಜ"
  },
  {
    "id": 39,
    "year": 971,
    "encoding": "Aksharameru",
    "place": "Nagavara",
    "lineNumber": 7,
    "posNumber": 5,
    "letter": "jyaṃ",
    "fileName": "971_Aksharameru_Nagavara_7_5_jyaṃ",
    "filePath": "jyaṃ/jyaṃ_form1/971_Aksharameru_Nagavara_7_5_jyaṃ.JPG",
    "kannadaWord": "ಜ್ಯಂ"
  },
  {
    "id": 40,
    "year": 971,
    "encoding": "Aksharameru",
    "place": "Nagavara",
    "lineNumber": 1,
    "posNumber": 5,
    "letter": "ka",
    "fileName": "971_Aksharameru_Nagavara_1_5_ka",
    "filePath": "ka/ka_form1/971_Aksharameru_Nagavara_1_5_ka.JPG",
    "kannadaWord": "ಕ"
  },
  {
    "id": 41,
    "year": 971,
    "encoding": "Aksharameru",
    "place": "Nagavara",
    "lineNumber": 2,
    "posNumber": 3,
    "letter": "ka",
    "fileName": "971_Aksharameru_Nagavara_2_3_ka",
    "filePath": "ka/ka_form1/971_Aksharameru_Nagavara_2_3_ka.JPG",
    "kannadaWord": "ಕ"
  },
  {
    "id": 42,
    "year": 971,
    "encoding": "Aksharameru",
    "place": "Nagavara",
    "lineNumber": 5,
    "posNumber": 2,
    "letter": "ka",
    "fileName": "971_Aksharameru_Nagavara_5_2_ka",
    "filePath": "ka/ka_form1/971_Aksharameru_Nagavara_5_2_ka.JPG",
    "kannadaWord": "ಕ"
  },
  {
    "id": 43,
    "year": 971,
    "encoding": "Aksharameru",
    "place": "Nagavara",
    "lineNumber": 5,
    "posNumber": 5,
    "letter": "ka",
    "fileName": "971_Aksharameru_Nagavara_5_5_ka",
    "filePath": "ka/ka_form1/971_Aksharameru_Nagavara_5_5_ka.JPG",
    "kannadaWord": "ಕ"
  },
  {
    "id": 44,
    "year": 971,
    "encoding": "Aksharameru",
    "place": "Nagavara",
    "lineNumber": 4,
    "posNumber": 9,
    "letter": "kra",
    "fileName": "971_Aksharameru_Nagavara_4_9_kra",
    "filePath": "kra/kra_form1/971_Aksharameru_Nagavara_4_9_kra.JPG",
    "kannadaWord": "ಕ್ರ"
  },
  {
    "id": 45,
    "year": 971,
    "encoding": "Aksharameru",
    "place": "Nagavara",
    "lineNumber": 1,
    "posNumber": 9,
    "letter": "ku",
    "fileName": "971_Aksharameru_Nagavara_1_9_ku",
    "filePath": "ku/ku_form1/971_Aksharameru_Nagavara_1_9_ku.JPG",
    "kannadaWord": "ಕು"
  },
  {
    "id": 46,
    "year": 971,
    "encoding": "Aksharameru",
    "place": "Nagavara",
    "lineNumber": 3,
    "posNumber": 10,
    "letter": "ku",
    "fileName": "971_Aksharameru_Nagavara_3_10_ku",
    "filePath": "ku/ku_form1/971_Aksharameru_Nagavara_3_10_ku.JPG",
    "kannadaWord": "ಕು"
  },
  {
    "id": 47,
    "year": 971,
    "encoding": "Aksharameru",
    "place": "Nagavara",
    "lineNumber": 1,
    "posNumber": 7,
    "letter": "kuṃ",
    "fileName": "971_Aksharameru_Nagavara_1_7_kuṃ",
    "filePath": "kuṃ/kuṃ_form1/971_Aksharameru_Nagavara_1_7_kuṃ.JPG",
    "kannadaWord": "ಕುಂ"
  },
  {
    "id": 48,
    "year": 971,
    "encoding": "Aksharameru",
    "place": "Nagavara",
    "lineNumber": 16,
    "posNumber": 4,
    "letter": "kā",
    "fileName": "971_Aksharameru_Nagavara_16_4_kā",
    "filePath": "kā/kā_form3/971_Aksharameru_Nagavara_16_4_kā.JPG",
    "kannadaWord": "ಕಾ"
  },
  {
    "id": 49,
    "year": 971,
    "encoding": "Aksharameru",
    "place": "Nagavara",
    "lineNumber": 3,
    "posNumber": 2,
    "letter": "kṣmi",
    "fileName": "971_Aksharameru_Nagavara_3_2_kṣmi",
    "filePath": "kṣmi/kṣmi_form1/971_Aksharameru_Nagavara_3_2_kṣmi.JPG",
    "kannadaWord": "ಕ್ಷ್ಮಿ"
  },
  {
    "id": 50,
    "year": 971,
    "encoding": "Aksharameru",
    "place": "Nagavara",
    "lineNumber": 3,
    "posNumber": 1,
    "letter": "la",
    "fileName": "971_Aksharameru_Nagavara_3_1_la",
    "filePath": "la/la_form1/971_Aksharameru_Nagavara_3_1_la.JPG",
    "kannadaWord": "ಲ"
  },
  {
    "id": 51,
    "year": 971,
    "encoding": "Aksharameru",
    "place": "Nagavara",
    "lineNumber": 3,
    "posNumber": 9,
    "letter": "li",
    "fileName": "971_Aksharameru_Nagavara_3_9_li",
    "filePath": "li/li_form1/971_Aksharameru_Nagavara_3_9_li.JPG",
    "kannadaWord": "ಲಿ"
  },
  {
    "id": 52,
    "year": 971,
    "encoding": "Aksharameru",
    "place": "Nagavara",
    "lineNumber": 5,
    "posNumber": 6,
    "letter": "li",
    "fileName": "971_Aksharameru_Nagavara_5_6_li",
    "filePath": "li/li_form1/971_Aksharameru_Nagavara_5_6_li.JPG",
    "kannadaWord": "ಲಿ"
  },
  {
    "id": 53,
    "year": 971,
    "encoding": "Aksharameru",
    "place": "Nagavara",
    "lineNumber": 3,
    "posNumber": 4,
    "letter": "lla",
    "fileName": "971_Aksharameru_Nagavara_3_4_lla",
    "filePath": "lla/lla_form1/971_Aksharameru_Nagavara_3_4_lla.JPG",
    "kannadaWord": "ಲ್ಲ"
  },
  {
    "id": 54,
    "year": 971,
    "encoding": "Aksharameru",
    "place": "Nagavara",
    "lineNumber": 3,
    "posNumber": 11,
    "letter": "lā",
    "fileName": "971_Aksharameru_Nagavara_3_11_lā",
    "filePath": "lā/lā_form1/971_Aksharameru_Nagavara_3_11_lā.JPG",
    "kannadaWord": "ಲಾ"
  },
  {
    "id": 55,
    "year": 971,
    "encoding": "Aksharameru",
    "place": "Nagavara",
    "lineNumber": 11,
    "posNumber": 8,
    "letter": "lĕ",
    "fileName": "971_Aksharameru_Nagavara_11_8_lĕ",
    "filePath": "lĕ/lĕ_form1/971_Aksharameru_Nagavara_11_8_lĕ.JPG",
    "kannadaWord": "ಲೆ"
  },
  {
    "id": 56,
    "year": 971,
    "encoding": "Aksharameru",
    "place": "Nagavara",
    "lineNumber": 9,
    "posNumber": 3,
    "letter": "l̤",
    "fileName": "971_Aksharameru_Nagavara_9_3_l̤",
    "filePath": "l̤/l̤_form1/971_Aksharameru_Nagavara_9_3_l̤.JPG",
    "kannadaWord": "ಳ್"
  },
  {
    "id": 57,
    "year": 971,
    "encoding": "Aksharameru",
    "place": "Nagavara",
    "lineNumber": 1,
    "posNumber": 12,
    "letter": "l̤a",
    "fileName": "971_Aksharameru_Nagavara_1_12_l̤a",
    "filePath": "l̤a/l̤a_form2/971_Aksharameru_Nagavara_1_12_l̤a.JPG",
    "kannadaWord": "ಳ"
  },
  {
    "id": 58,
    "year": 971,
    "encoding": "Aksharameru",
    "place": "Nagavara",
    "lineNumber": 2,
    "posNumber": 5,
    "letter": "l̤a",
    "fileName": "971_Aksharameru_Nagavara_2_5_l̤a",
    "filePath": "l̤a/l̤a_form2/971_Aksharameru_Nagavara_2_5_l̤a.JPG",
    "kannadaWord": "ಳ"
  },
  {
    "id": 59,
    "year": 971,
    "encoding": "Aksharameru",
    "place": "Nagavara",
    "lineNumber": 2,
    "posNumber": 7,
    "letter": "l̤a",
    "fileName": "971_Aksharameru_Nagavara_2_7_l̤a",
    "filePath": "l̤a/l̤a_form2/971_Aksharameru_Nagavara_2_7_l̤a.JPG",
    "kannadaWord": "ಳ"
  },
  {
    "id": 60,
    "year": 971,
    "encoding": "Aksharameru",
    "place": "Nagavara",
    "lineNumber": 15,
    "posNumber": 4,
    "letter": "l̤u",
    "fileName": "971_Aksharameru_Nagavara_15_4_l̤u",
    "filePath": "l̤u/l̤u_form2/971_Aksharameru_Nagavara_15_4_l̤u.JPG",
    "kannadaWord": "ಳು"
  },
  {
    "id": 61,
    "year": 971,
    "encoding": "Aksharameru",
    "place": "Nagavara",
    "lineNumber": 14,
    "posNumber": 2,
    "letter": "l̤ŏ",
    "fileName": "971_Aksharameru_Nagavara_14_2_l̤ŏ",
    "filePath": "l̤ŏ/l̤ŏ_form1/971_Aksharameru_Nagavara_14_2_l̤ŏ.JPG",
    "kannadaWord": "ಳೊ"
  },
  {
    "id": 62,
    "year": 971,
    "encoding": "Aksharameru",
    "place": "Nagavara",
    "lineNumber": 12,
    "posNumber": 3,
    "letter": "ma",
    "fileName": "971_Aksharameru_Nagavara_12_3_ma",
    "filePath": "ma/ma_form3/971_Aksharameru_Nagavara_12_3_ma.JPG",
    "kannadaWord": "ಮ"
  },
  {
    "id": 63,
    "year": 971,
    "encoding": "Aksharameru",
    "place": "Nagavara",
    "lineNumber": 15,
    "posNumber": 5,
    "letter": "ma",
    "fileName": "971_Aksharameru_Nagavara_15_5_ma",
    "filePath": "ma/ma_form3/971_Aksharameru_Nagavara_15_5_ma.JPG",
    "kannadaWord": "ಮ"
  },
  {
    "id": 64,
    "year": 971,
    "encoding": "Aksharameru",
    "place": "Nagavara",
    "lineNumber": 1,
    "posNumber": 3,
    "letter": "ma",
    "fileName": "971_Aksharameru_Nagavara_1_3_ma",
    "filePath": "ma/ma_form3/971_Aksharameru_Nagavara_1_3_ma.JPG",
    "kannadaWord": "ಮ"
  },
  {
    "id": 65,
    "year": 971,
    "encoding": "Aksharameru",
    "place": "Nagavara",
    "lineNumber": 4,
    "posNumber": 10,
    "letter": "ma",
    "fileName": "971_Aksharameru_Nagavara_4_10_ma",
    "filePath": "ma/ma_form3/971_Aksharameru_Nagavara_4_10_ma.JPG",
    "kannadaWord": "ಮ"
  },
  {
    "id": 66,
    "year": 971,
    "encoding": "Aksharameru",
    "place": "Nagavara",
    "lineNumber": 3,
    "posNumber": 6,
    "letter": "mā",
    "fileName": "971_Aksharameru_Nagavara_3_6_mā",
    "filePath": "mā/mā_form1/971_Aksharameru_Nagavara_3_6_mā.JPG",
    "kannadaWord": "ಮಾ"
  },
  {
    "id": 67,
    "year": 971,
    "encoding": "Aksharameru",
    "place": "Nagavara",
    "lineNumber": 9,
    "posNumber": 4,
    "letter": "mā",
    "fileName": "971_Aksharameru_Nagavara_9_4_mā",
    "filePath": "mā/mā_form1/971_Aksharameru_Nagavara_9_4_mā.JPG",
    "kannadaWord": "ಮಾ"
  },
  {
    "id": 68,
    "year": 971,
    "encoding": "Aksharameru",
    "place": "Nagavara",
    "lineNumber": 6,
    "posNumber": 3,
    "letter": "mŏ",
    "fileName": "971_Aksharameru_Nagavara_6_3_mŏ",
    "filePath": "mŏ/mŏ_form1/971_Aksharameru_Nagavara_6_3_mŏ.JPG",
    "kannadaWord": "ಮೊ"
  },
  {
    "id": 69,
    "year": 971,
    "encoding": "Aksharameru",
    "place": "Nagavara",
    "lineNumber": 2,
    "posNumber": 2,
    "letter": "na",
    "fileName": "971_Aksharameru_Nagavara_2_2_na",
    "filePath": "na/na_form1/971_Aksharameru_Nagavara_2_2_na.JPG",
    "kannadaWord": "ನ"
  },
  {
    "id": 70,
    "year": 971,
    "encoding": "Aksharameru",
    "place": "Nagavara",
    "lineNumber": 13,
    "posNumber": 5,
    "letter": "na",
    "fileName": "971_Aksharameru_Nagavara_13_5_na",
    "filePath": "na/na_form2/971_Aksharameru_Nagavara_13_5_na.JPG",
    "kannadaWord": "ನ"
  },
  {
    "id": 71,
    "year": 971,
    "encoding": "Aksharameru",
    "place": "Nagavara",
    "lineNumber": 2,
    "posNumber": 6,
    "letter": "ni",
    "fileName": "971_Aksharameru_Nagavara_2_6_ni",
    "filePath": "ni/ni_form2/971_Aksharameru_Nagavara_2_6_ni.JPG",
    "kannadaWord": "ನಿ"
  },
  {
    "id": 72,
    "year": 971,
    "encoding": "Aksharameru",
    "place": "Nagavara",
    "lineNumber": 14,
    "posNumber": 8,
    "letter": "nā",
    "fileName": "971_Aksharameru_Nagavara_14_8_nā",
    "filePath": "nā/nā_form1/971_Aksharameru_Nagavara_14_8_nā.JPG",
    "kannadaWord": "ನಾ"
  },
  {
    "id": 73,
    "year": 971,
    "encoding": "Aksharameru",
    "place": "Nagavara",
    "lineNumber": 8,
    "posNumber": 7,
    "letter": "pa",
    "fileName": "971_Aksharameru_Nagavara_8_7_pa",
    "filePath": "pa/pa_form2/971_Aksharameru_Nagavara_8_7_pa.JPG",
    "kannadaWord": "ಪ"
  },
  {
    "id": 74,
    "year": 971,
    "encoding": "Aksharameru",
    "place": "Nagavara",
    "lineNumber": 9,
    "posNumber": 7,
    "letter": "pa",
    "fileName": "971_Aksharameru_Nagavara_9_7_pa",
    "filePath": "pa/pa_form2/971_Aksharameru_Nagavara_9_7_pa.JPG",
    "kannadaWord": "ಪ"
  },
  {
    "id": 75,
    "year": 971,
    "encoding": "Aksharameru",
    "place": "Nagavara",
    "lineNumber": 15,
    "posNumber": 1,
    "letter": "pra",
    "fileName": "971_Aksharameru_Nagavara_15_1_pra",
    "filePath": "pra/pra_form1/971_Aksharameru_Nagavara_15_1_pra.JPG",
    "kannadaWord": "ಪ್ರ"
  },
  {
    "id": 76,
    "year": 971,
    "encoding": "Aksharameru",
    "place": "Nagavara",
    "lineNumber": 1,
    "posNumber": 13,
    "letter": "pra",
    "fileName": "971_Aksharameru_Nagavara_1_13_pra",
    "filePath": "pra/pra_form1/971_Aksharameru_Nagavara_1_13_pra.JPG",
    "kannadaWord": "ಪ್ರ"
  },
  {
    "id": 77,
    "year": 971,
    "encoding": "Aksharameru",
    "place": "Nagavara",
    "lineNumber": 8,
    "posNumber": 5,
    "letter": "pra",
    "fileName": "971_Aksharameru_Nagavara_8_5_pra",
    "filePath": "pra/pra_form1/971_Aksharameru_Nagavara_8_5_pra.JPG",
    "kannadaWord": "ಪ್ರ"
  },
  {
    "id": 78,
    "year": 971,
    "encoding": "Aksharameru",
    "place": "Nagavara",
    "lineNumber": 13,
    "posNumber": 3,
    "letter": "ra",
    "fileName": "971_Aksharameru_Nagavara_13_3_ra",
    "filePath": "ra/ra_form1/971_Aksharameru_Nagavara_13_3_ra.JPG",
    "kannadaWord": "ರ"
  },
  {
    "id": 79,
    "year": 971,
    "encoding": "Aksharameru",
    "place": "Nagavara",
    "lineNumber": 14,
    "posNumber": 6,
    "letter": "ra",
    "fileName": "971_Aksharameru_Nagavara_14_6_ra",
    "filePath": "ra/ra_form1/971_Aksharameru_Nagavara_14_6_ra.JPG",
    "kannadaWord": "ರ"
  },
  {
    "id": 80,
    "year": 971,
    "encoding": "Aksharameru",
    "place": "Nagavara",
    "lineNumber": 4,
    "posNumber": 12,
    "letter": "ra",
    "fileName": "971_Aksharameru_Nagavara_4_12_ra",
    "filePath": "ra/ra_form1/971_Aksharameru_Nagavara_4_12_ra.JPG",
    "kannadaWord": "ರ"
  },
  {
    "id": 81,
    "year": 971,
    "encoding": "Aksharameru",
    "place": "Nagavara",
    "lineNumber": 4,
    "posNumber": 3,
    "letter": "ra",
    "fileName": "971_Aksharameru_Nagavara_4_3_ra",
    "filePath": "ra/ra_form1/971_Aksharameru_Nagavara_4_3_ra.JPG",
    "kannadaWord": "ರ"
  },
  {
    "id": 82,
    "year": 971,
    "encoding": "Aksharameru",
    "place": "Nagavara",
    "lineNumber": 7,
    "posNumber": 3,
    "letter": "ra",
    "fileName": "971_Aksharameru_Nagavara_7_3_ra",
    "filePath": "ra/ra_form1/971_Aksharameru_Nagavara_7_3_ra.JPG",
    "kannadaWord": "ರ"
  },
  {
    "id": 83,
    "year": 971,
    "encoding": "Aksharameru",
    "place": "Nagavara",
    "lineNumber": 9,
    "posNumber": 1,
    "letter": "ra",
    "fileName": "971_Aksharameru_Nagavara_9_1_ra",
    "filePath": "ra/ra_form1/971_Aksharameru_Nagavara_9_1_ra.JPG",
    "kannadaWord": "ರ"
  },
  {
    "id": 84,
    "year": 971,
    "encoding": "Aksharameru",
    "place": "Nagavara",
    "lineNumber": 1,
    "posNumber": 6,
    "letter": "ri",
    "fileName": "971_Aksharameru_Nagavara_1_6_ri",
    "filePath": "ri/ri_form1/971_Aksharameru_Nagavara_1_6_ri.JPG",
    "kannadaWord": "ರಿ"
  },
  {
    "id": 85,
    "year": 971,
    "encoding": "Aksharameru",
    "place": "Nagavara",
    "lineNumber": 4,
    "posNumber": 8,
    "letter": "ri",
    "fileName": "971_Aksharameru_Nagavara_4_8_ri",
    "filePath": "ri/ri_form1/971_Aksharameru_Nagavara_4_8_ri.JPG",
    "kannadaWord": "ರಿ"
  },
  {
    "id": 86,
    "year": 971,
    "encoding": "Aksharameru",
    "place": "Nagavara",
    "lineNumber": 7,
    "posNumber": 10,
    "letter": "ri",
    "fileName": "971_Aksharameru_Nagavara_7_10_ri",
    "filePath": "ri/ri_form1/971_Aksharameru_Nagavara_7_10_ri.JPG",
    "kannadaWord": "ರಿ"
  },
  {
    "id": 87,
    "year": 971,
    "encoding": "Aksharameru",
    "place": "Nagavara",
    "lineNumber": 2,
    "posNumber": 4,
    "letter": "rā",
    "fileName": "971_Aksharameru_Nagavara_2_4_rā",
    "filePath": "rā/rā_form1/971_Aksharameru_Nagavara_2_4_rā.JPG",
    "kannadaWord": "ರಾ"
  },
  {
    "id": 88,
    "year": 971,
    "encoding": "Aksharameru",
    "place": "Nagavara",
    "lineNumber": 7,
    "posNumber": 4,
    "letter": "rā",
    "fileName": "971_Aksharameru_Nagavara_7_4_rā",
    "filePath": "rā/rā_form1/971_Aksharameru_Nagavara_7_4_rā.JPG",
    "kannadaWord": "ರಾ"
  },
  {
    "id": 89,
    "year": 971,
    "encoding": "Aksharameru",
    "place": "Nagavara",
    "lineNumber": 16,
    "posNumber": 6,
    "letter": "sa",
    "fileName": "971_Aksharameru_Nagavara_16_6_sa",
    "filePath": "sa/sa_form1/971_Aksharameru_Nagavara_16_6_sa.JPG",
    "kannadaWord": "ಸ"
  },
  {
    "id": 90,
    "year": 971,
    "encoding": "Aksharameru",
    "place": "Nagavara",
    "lineNumber": 17,
    "posNumber": 1,
    "letter": "sa",
    "fileName": "971_Aksharameru_Nagavara_17_1_sa",
    "filePath": "sa/sa_form3/971_Aksharameru_Nagavara_17_1_sa.JPG",
    "kannadaWord": "ಸ"
  },
  {
    "id": 91,
    "year": 971,
    "encoding": "Aksharameru",
    "place": "Nagavara",
    "lineNumber": 1,
    "posNumber": 11,
    "letter": "sta",
    "fileName": "971_Aksharameru_Nagavara_1_11_sta",
    "filePath": "sta/sta_form2/971_Aksharameru_Nagavara_1_11_sta.JPG",
    "kannadaWord": "ಸ್ತ"
  },
  {
    "id": 92,
    "year": 971,
    "encoding": "Aksharameru",
    "place": "Nagavara",
    "lineNumber": 1,
    "posNumber": 2,
    "letter": "sti",
    "fileName": "971_Aksharameru_Nagavara_1_2_sti",
    "filePath": "sti/sti_form1/971_Aksharameru_Nagavara_1_2_sti.JPG",
    "kannadaWord": "ಸ್ತಿ"
  },
  {
    "id": 93,
    "year": 971,
    "encoding": "Aksharameru",
    "place": "Nagavara",
    "lineNumber": 1,
    "posNumber": 1,
    "letter": "sva",
    "fileName": "971_Aksharameru_Nagavara_1_1_sva",
    "filePath": "sva/sva_form1/971_Aksharameru_Nagavara_1_1_sva.JPG",
    "kannadaWord": "ಸ್ವ"
  },
  {
    "id": 94,
    "year": 971,
    "encoding": "Aksharameru",
    "place": "Nagavara",
    "lineNumber": 7,
    "posNumber": 2,
    "letter": "ta",
    "fileName": "971_Aksharameru_Nagavara_7_2_ta",
    "filePath": "ta/ta_form2/971_Aksharameru_Nagavara_7_2_ta.JPG",
    "kannadaWord": "ತ"
  },
  {
    "id": 95,
    "year": 971,
    "encoding": "Aksharameru",
    "place": "Nagavara",
    "lineNumber": 8,
    "posNumber": 8,
    "letter": "ti",
    "fileName": "971_Aksharameru_Nagavara_8_8_ti",
    "filePath": "ti/ti_form2/971_Aksharameru_Nagavara_8_8_ti.JPG",
    "kannadaWord": "ತಿ"
  },
  {
    "id": 96,
    "year": 971,
    "encoding": "Aksharameru",
    "place": "Nagavara",
    "lineNumber": 8,
    "posNumber": 12,
    "letter": "tsa",
    "fileName": "971_Aksharameru_Nagavara_8_12_tsa",
    "filePath": "tsa/tsa_form1/971_Aksharameru_Nagavara_8_12_tsa.JPG",
    "kannadaWord": "ತ್ಸ"
  },
  {
    "id": 97,
    "year": 971,
    "encoding": "Aksharameru",
    "place": "Nagavara",
    "lineNumber": 16,
    "posNumber": 7,
    "letter": "ttu",
    "fileName": "971_Aksharameru_Nagavara_16_7_ttu",
    "filePath": "ttu/ttu_form1/971_Aksharameru_Nagavara_16_7_ttu.JPG",
    "kannadaWord": "ತ್ತು"
  },
  {
    "id": 98,
    "year": 971,
    "encoding": "Aksharameru",
    "place": "Nagavara",
    "lineNumber": 6,
    "posNumber": 1,
    "letter": "u",
    "fileName": "971_Aksharameru_Nagavara_6_1_u",
    "filePath": "u/u_form1/971_Aksharameru_Nagavara_6_1_u.JPG",
    "kannadaWord": "ಉ"
  },
  {
    "id": 99,
    "year": 971,
    "encoding": "Aksharameru",
    "place": "Nagavara",
    "lineNumber": 10,
    "posNumber": 1,
    "letter": "va",
    "fileName": "971_Aksharameru_Nagavara_10_1_va",
    "filePath": "va/va_form1/971_Aksharameru_Nagavara_10_1_va.JPG",
    "kannadaWord": "ವ"
  },
  {
    "id": 100,
    "year": 971,
    "encoding": "Aksharameru",
    "place": "Nagavara",
    "lineNumber": 5,
    "posNumber": 11,
    "letter": "va",
    "fileName": "971_Aksharameru_Nagavara_5_11_va",
    "filePath": "va/va_form1/971_Aksharameru_Nagavara_5_11_va.JPG",
    "kannadaWord": "ವ"
  },
  {
    "id": 101,
    "year": 971,
    "encoding": "Aksharameru",
    "place": "Nagavara",
    "lineNumber": 8,
    "posNumber": 11,
    "letter": "va",
    "fileName": "971_Aksharameru_Nagavara_8_11_va",
    "filePath": "va/va_form1/971_Aksharameru_Nagavara_8_11_va.JPG",
    "kannadaWord": "ವ"
  },
  {
    "id": 102,
    "year": 971,
    "encoding": "Aksharameru",
    "place": "Nagavara",
    "lineNumber": 3,
    "posNumber": 3,
    "letter": "va",
    "fileName": "971_Aksharameru_Nagavara_3_3_va",
    "filePath": "va/va_form2/971_Aksharameru_Nagavara_3_3_va.JPG",
    "kannadaWord": "ವ"
  },
  {
    "id": 103,
    "year": 971,
    "encoding": "Aksharameru",
    "place": "Nagavara",
    "lineNumber": 2,
    "posNumber": 10,
    "letter": "vi",
    "fileName": "971_Aksharameru_Nagavara_2_10_vi",
    "filePath": "vi/vi_form2/971_Aksharameru_Nagavara_2_10_vi.JPG",
    "kannadaWord": "ವಿ"
  },
  {
    "id": 104,
    "year": 971,
    "encoding": "Aksharameru",
    "place": "Nagavara",
    "lineNumber": 10,
    "posNumber": 3,
    "letter": "vu",
    "fileName": "971_Aksharameru_Nagavara_10_3_vu",
    "filePath": "vu/vu_form2/971_Aksharameru_Nagavara_10_3_vu.JPG",
    "kannadaWord": "ವು"
  },
  {
    "id": 105,
    "year": 971,
    "encoding": "Aksharameru",
    "place": "Nagavara",
    "lineNumber": 12,
    "posNumber": 2,
    "letter": "ya",
    "fileName": "971_Aksharameru_Nagavara_12_2_ya",
    "filePath": "ya/ya_form1/971_Aksharameru_Nagavara_12_2_ya.JPG",
    "kannadaWord": "ಯ"
  },
  {
    "id": 106,
    "year": 971,
    "encoding": "Aksharameru",
    "place": "Nagavara",
    "lineNumber": 2,
    "posNumber": 12,
    "letter": "ya",
    "fileName": "971_Aksharameru_Nagavara_2_12_ya",
    "filePath": "ya/ya_form1/971_Aksharameru_Nagavara_2_12_ya.JPG",
    "kannadaWord": "ಯ"
  },
  {
    "id": 107,
    "year": 971,
    "encoding": "Aksharameru",
    "place": "Nagavara",
    "lineNumber": 11,
    "posNumber": 1,
    "letter": "yaṃ",
    "fileName": "971_Aksharameru_Nagavara_11_1_yaṃ",
    "filePath": "yaṃ/yaṃ_form1/971_Aksharameru_Nagavara_11_1_yaṃ.JPG",
    "kannadaWord": "ಯಂ"
  },
  {
    "id": 108,
    "year": 971,
    "encoding": "Aksharameru",
    "place": "Nagavara",
    "lineNumber": 5,
    "posNumber": 4,
    "letter": "yaṃ",
    "fileName": "971_Aksharameru_Nagavara_5_4_yaṃ",
    "filePath": "yaṃ/yaṃ_form1/971_Aksharameru_Nagavara_5_4_yaṃ.JPG",
    "kannadaWord": "ಯಂ"
  },
  {
    "id": 109,
    "year": 971,
    "encoding": "Aksharameru",
    "place": "Nagavara",
    "lineNumber": 5,
    "posNumber": 7,
    "letter": "yu",
    "fileName": "971_Aksharameru_Nagavara_5_7_yu",
    "filePath": "yu/yu_form1/971_Aksharameru_Nagavara_5_7_yu.JPG",
    "kannadaWord": "ಯು"
  },
  {
    "id": 110,
    "year": 971,
    "encoding": "Aksharameru",
    "place": "Nagavara",
    "lineNumber": 12,
    "posNumber": 8,
    "letter": "yya",
    "fileName": "971_Aksharameru_Nagavara_12_8_yya",
    "filePath": "yya/yya_form1/971_Aksharameru_Nagavara_12_8_yya.JPG",
    "kannadaWord": "ಯ್ಯ"
  },
  {
    "id": 111,
    "year": 971,
    "encoding": "Aksharameru",
    "place": "Nagavara",
    "lineNumber": 13,
    "posNumber": 4,
    "letter": "yya",
    "fileName": "971_Aksharameru_Nagavara_13_4_yya",
    "filePath": "yya/yya_form2/971_Aksharameru_Nagavara_13_4_yya.JPG",
    "kannadaWord": "ಯ್ಯ"
  },
  {
    "id": 112,
    "year": 971,
    "encoding": "Aksharameru",
    "place": "Nagavara",
    "lineNumber": 17,
    "posNumber": 3,
    "letter": "yā",
    "fileName": "971_Aksharameru_Nagavara_17_3_yā",
    "filePath": "yā/yā_form1/971_Aksharameru_Nagavara_17_3_yā.JPG",
    "kannadaWord": "ಯಾ"
  },
  {
    "id": 113,
    "year": 971,
    "encoding": "Aksharameru",
    "place": "Nagavara",
    "lineNumber": 14,
    "posNumber": 5,
    "letter": "ĕ",
    "fileName": "971_Aksharameru_Nagavara_14_5_ĕ",
    "filePath": "ĕ/ĕ_form2/971_Aksharameru_Nagavara_14_5_ĕ.JPG",
    "kannadaWord": "ಎ"
  },
  {
    "id": 114,
    "year": 971,
    "encoding": "Aksharameru",
    "place": "Nagavara",
    "lineNumber": 14,
    "posNumber": 9,
    "letter": "ḍa",
    "fileName": "971_Aksharameru_Nagavara_14_9_ḍa",
    "filePath": "ḍa/ḍa_form1/971_Aksharameru_Nagavara_14_9_ḍa.JPG",
    "kannadaWord": "ಡ"
  },
  {
    "id": 115,
    "year": 971,
    "encoding": "Aksharameru",
    "place": "Nagavara",
    "lineNumber": 14,
    "posNumber": 7,
    "letter": "ḍu",
    "fileName": "971_Aksharameru_Nagavara_14_7_ḍu",
    "filePath": "ḍu/ḍu_form3/971_Aksharameru_Nagavara_14_7_ḍu.JPG",
    "kannadaWord": "ಡು"
  },
  {
    "id": 116,
    "year": 971,
    "encoding": "Aksharameru",
    "place": "Nagavara",
    "lineNumber": 16,
    "posNumber": 3,
    "letter": "ḻĕ",
    "fileName": "971_Aksharameru_Nagavara_16_3_ḻĕ",
    "filePath": "ḻĕ/ḻĕ_form1/971_Aksharameru_Nagavara_16_3_ḻĕ.JPG",
    "kannadaWord": "ೞೆ"
  },
  {
    "id": 117,
    "year": 971,
    "encoding": "Aksharameru",
    "place": "Nagavara",
    "lineNumber": 11,
    "posNumber": 3,
    "letter": "ṇa",
    "fileName": "971_Aksharameru_Nagavara_11_3_ṇa",
    "filePath": "ṇa/ṇa_form2/971_Aksharameru_Nagavara_11_3_ṇa.JPG",
    "kannadaWord": "ಣ"
  },
  {
    "id": 118,
    "year": 971,
    "encoding": "Aksharameru",
    "place": "Nagavara",
    "lineNumber": 4,
    "posNumber": 4,
    "letter": "ṇa",
    "fileName": "971_Aksharameru_Nagavara_4_4_ṇa",
    "filePath": "ṇa/ṇa_form2/971_Aksharameru_Nagavara_4_4_ṇa.JPG",
    "kannadaWord": "ಣ"
  },
  {
    "id": 119,
    "year": 971,
    "encoding": "Aksharameru",
    "place": "Nagavara",
    "lineNumber": 4,
    "posNumber": 6,
    "letter": "ṇa",
    "fileName": "971_Aksharameru_Nagavara_4_6_ṇa",
    "filePath": "ṇa/ṇa_form2/971_Aksharameru_Nagavara_4_6_ṇa.JPG",
    "kannadaWord": "ಣ"
  },
  {
    "id": 120,
    "year": 971,
    "encoding": "Aksharameru",
    "place": "Nagavara",
    "lineNumber": 5,
    "posNumber": 10,
    "letter": "ṇu",
    "fileName": "971_Aksharameru_Nagavara_5_10_ṇu",
    "filePath": "ṇu/ṇu_form1/971_Aksharameru_Nagavara_5_10_ṇu.JPG",
    "kannadaWord": "ಣು"
  },
  {
    "id": 121,
    "year": 971,
    "encoding": "Aksharameru",
    "place": "Nagavara",
    "lineNumber": 6,
    "posNumber": 6,
    "letter": "ṇḍa",
    "fileName": "971_Aksharameru_Nagavara_6_6_ṇḍa",
    "filePath": "ṇḍa/ṇḍa_form1/971_Aksharameru_Nagavara_6_6_ṇḍa.JPG",
    "kannadaWord": "ಣ್ಡ"
  },
  {
    "id": 122,
    "year": 971,
    "encoding": "Aksharameru",
    "place": "Nagavara",
    "lineNumber": 10,
    "posNumber": 4,
    "letter": "ṇḍaṃ",
    "fileName": "971_Aksharameru_Nagavara_10_4_ṇḍaṃ",
    "filePath": "ṇḍaṃ/ṇḍaṃ_form1/971_Aksharameru_Nagavara_10_4_ṇḍaṃ.JPG",
    "kannadaWord": "ಣ್ಡಂ"
  },
  {
    "id": 123,
    "year": 971,
    "encoding": "Aksharameru",
    "place": "Nagavara",
    "lineNumber": 8,
    "posNumber": 1,
    "letter": "ṣa",
    "fileName": "971_Aksharameru_Nagavara_8_1_ṣa",
    "filePath": "ṣa/ṣa_form1/971_Aksharameru_Nagavara_8_1_ṣa.JPG",
    "kannadaWord": "ಷ"
  }
]