[
  {
    "id": 1,
    "key": "Symbols",
    "isAvailable": true,
    "letterForms": [
      {
        "id": 1,
        "form": "Symbols",
        "path": "Symbols/1306_DB52_Isturu_Anjaneya.JPG",
        "year": 1306
      },
      {
        "id": 2,
        "form": "Symbols",
        "path": "Symbols/1306_DB52_Isturu_Anjaneya_invert.JPG",
        "year": 1306
      },
      {
        "id": 3,
        "form": "Symbols",
        "path": "Symbols/1306_DB52_Isturu_cow.JPG",
        "year": 1306
      },
      {
        "id": 4,
        "form": "Symbols",
        "path": "Symbols/1306_DB52_Isturu_Cow_-nvert.JPG",
        "year": 1306
      },
      {
        "id": 5,
        "form": "Symbols",
        "path": "Symbols/1306_DB52_Isturu_Gandaberunda.JPG",
        "year": 1306
      },
      {
        "id": 6,
        "form": "Symbols",
        "path": "Symbols/1306_DB52_Isturu_Gandaberunda_invert.JPG",
        "year": 1306
      },
      {
        "id": 7,
        "form": "Symbols",
        "path": "Symbols/1306_DB52_Isturu_Horse.JPG",
        "year": 1306
      },
      {
        "id": 8,
        "form": "Symbols",
        "path": "Symbols/1306_DB52_Isturu_Horse_invert.JPG",
        "year": 1306
      },
      {
        "id": 9,
        "form": "Symbols",
        "path": "Symbols/1306_DB52_Isturu_Shivalinga.JPG",
        "year": 1306
      },
      {
        "id": 10,
        "form": "Symbols",
        "path": "Symbols/1306_DB52_Isturu_Tiger.JPG",
        "year": 1306
      },
      {
        "id": 11,
        "form": "Symbols",
        "path": "Symbols/1306_DB52_Isturu_Tiger_gandaberunda.JPG",
        "year": 1306
      },
      {
        "id": 12,
        "form": "Symbols",
        "path": "Symbols/1306_DB52_Isturu_Upper_porstion.JPG",
        "year": 1306
      },
      {
        "id": 13,
        "form": "Symbols",
        "path": "Symbols/1306_DB52_Isturu_Upper_porstion_invert.JPG",
        "year": 1306
      },
      {
        "id": 14,
        "form": "Symbols",
        "path": "Symbols/1306_DB52_Isturu_z.JPG",
        "year": 1306
      },
      {
        "id": 15,
        "form": "Symbols",
        "path": "Symbols/1336_Bn110_Byadarahalli_Gandaberunda.JPG",
        "year": 1336
      },
      {
        "id": 16,
        "form": "Symbols",
        "path": "Symbols/1336_Bn110_Byadarahalli_Gandaberunda_tiger.JPG",
        "year": 1336
      },
      {
        "id": 17,
        "form": "Symbols",
        "path": "Symbols/1336_Bn110_Byadarahalli_Lion_man.JPG",
        "year": 1336
      },
      {
        "id": 18,
        "form": "Symbols",
        "path": "Symbols/1336_Bn110_Byadarahalli_Tiger.JPG",
        "year": 1336
      },
      {
        "id": 19,
        "form": "Symbols",
        "path": "Symbols/1336_Bn110_Byadarahalli_upper porstion.JPG",
        "year": 1336
      },
      {
        "id": 20,
        "form": "Symbols",
        "path": "Symbols/1342_BN21_Jakkur_MOON.jpg",
        "year": 1342
      },
      {
        "id": 21,
        "form": "Symbols",
        "path": "Symbols/1342_BN21_Jakkur_OM.jpg",
        "year": 1342
      },
      {
        "id": 22,
        "form": "Symbols",
        "path": "Symbols/1342_BN21_Jakkur_SUN.jpg",
        "year": 1342
      },
      {
        "id": 23,
        "form": "Symbols",
        "path": "Symbols/1342_BN24_Ganigarahalli_12_3_+.JPG",
        "year": 1342
      },
      {
        "id": 24,
        "form": "Symbols",
        "path": "Symbols/1342_BN24_Ganigarahalli_Gandaberunda.JPG",
        "year": 1342
      },
      {
        "id": 25,
        "form": "Symbols",
        "path": "Symbols/1342_BN24_Ganigarahalli_Gandaberunda_Tiger.JPG",
        "year": 1342
      },
      {
        "id": 26,
        "form": "Symbols",
        "path": "Symbols/1342_BN24_Ganigarahalli_Moon.JPG",
        "year": 1342
      },
      {
        "id": 27,
        "form": "Symbols",
        "path": "Symbols/1342_BN24_Ganigarahalli_Om.JPG",
        "year": 1342
      },
      {
        "id": 28,
        "form": "Symbols",
        "path": "Symbols/1342_BN24_Ganigarahalli_Sun.JPG",
        "year": 1342
      },
      {
        "id": 29,
        "form": "Symbols",
        "path": "Symbols/1342_BN24_Ganigarahalli_Tiger.JPG",
        "year": 1342
      },
      {
        "id": 30,
        "form": "Symbols",
        "path": "Symbols/1342_BN24_Ganigarahalli_unkown_symbol.JPG",
        "year": 1342
      },
      {
        "id": 31,
        "form": "Symbols",
        "path": "Symbols/1363_BN81_AgaraMuseum_1_1_0_symbol.JPG",
        "year": 1363
      },
      {
        "id": 32,
        "form": "Symbols",
        "path": "Symbols/1382_DV57_Chikkajala_Chakra.JPG",
        "year": 1382
      },
      {
        "id": 33,
        "form": "Symbols",
        "path": "Symbols/1382_DV57_Chikkajala_cow.JPG",
        "year": 1382
      },
      {
        "id": 34,
        "form": "Symbols",
        "path": "Symbols/1382_DV57_Chikkajala_Moon.JPG",
        "year": 1382
      },
      {
        "id": 35,
        "form": "Symbols",
        "path": "Symbols/1382_DV57_Chikkajala_Shankha.JPG",
        "year": 1382
      },
      {
        "id": 36,
        "form": "Symbols",
        "path": "Symbols/1382_DV57_Chikkajala_Shankha_chakra.JPG",
        "year": 1382
      },
      {
        "id": 37,
        "form": "Symbols",
        "path": "Symbols/1382_DV57_Chikkajala_sun.JPG",
        "year": 1382
      },
      {
        "id": 38,
        "form": "Symbols",
        "path": "Symbols/1382_DV57_Chikkajala_tirunama.JPG",
        "year": 1382
      },
      {
        "id": 39,
        "form": "Symbols",
        "path": "Symbols/1382_DV57_Chikkajala_upper portion.JPG",
        "year": 1382
      },
      {
        "id": 40,
        "form": "Symbol I",
        "path": "Symbols/Symbol I/1329_IthDar_Kadatanamale_12_7_I.JPG",
        "year": 1329
      },
      {
        "id": 41,
        "form": "Symbol I",
        "path": "Symbols/Symbol I/1329_IthDar_Kadatanamale_19_5_I.JPG",
        "year": 1329
      },
      {
        "id": 42,
        "form": "Symbol I",
        "path": "Symbols/Symbol I/1329_IthDar_Kadatanamale_19_6_I.JPG",
        "year": 1329
      },
      {
        "id": 43,
        "form": "Symbol I",
        "path": "Symbols/Symbol I/1329_IthDar_Kadatanamale_8_9_I.JPG",
        "year": 1329
      },
      {
        "id": 44,
        "form": "Symbol I",
        "path": "Symbols/Symbol I/1336_DV46_Sadenahalli_2_7_I.JPG",
        "year": 1336
      },
      {
        "id": 45,
        "form": "Symbol I",
        "path": "Symbols/Symbol I/1336_DV46_Sadenahalli_3_9_I.JPG",
        "year": 1336
      },
      {
        "id": 46,
        "form": "Symbol I",
        "path": "Symbols/Symbol I/1336_DV46_Sadenahalli_4_9_I.JPG",
        "year": 1336
      },
      {
        "id": 47,
        "form": "Symbol I",
        "path": "Symbols/Symbol I/1363_BN81_AgaraMuseum_17_10_I.JPG",
        "year": 1363
      },
      {
        "id": 48,
        "form": "Symbol I",
        "path": "Symbols/Symbol I/1363_BN81_AgaraMuseum_2_8_I.JPG",
        "year": 1363
      },
      {
        "id": 49,
        "form": "Symbol I",
        "path": "Symbols/Symbol I/1363_BN81_AgaraMuseum_3_2_I.JPG",
        "year": 1363
      },
      {
        "id": 50,
        "form": "Symbol I",
        "path": "Symbols/Symbol I/1388_MG20_HuleLinganaAre_2_9_I.JPG",
        "year": 1388
      }
    ],
    "IASTform": "",
    "forms": []
  }
]